<?xml version="1.0" encoding="UTF-8"?><i><chatserver>chat.bilibili.com</chatserver><chatid>116417370</chatid><mission>0</mission><maxlimit>500</maxlimit><state>0</state><real_name>0</real_name><source>k-v</source><d p="4.34100,1,25,16777215,1606661025,0,715de77a,41690778951483397">1</d><d p="44.91800,1,25,16777215,1606557436,0,6107bd3,41636468520124419">杨紫</d><d p="106.90100,1,25,16777215,1606361678,0,b769a03c,41533834842865671">孙家坡</d><d p="95.10300,1,25,16777215,1606361672,0,b769a03c,41533831785218055">孙家坡好评</d><d p="84.18200,1,25,16777215,1606361666,0,b769a03c,41533828908974087">637好评</d><d p="55.01900,1,25,16777215,1606361652,0,b769a03c,41533821270097927">古城</d><d p="38.56000,1,25,16777215,1606361643,0,b769a03c,41533816941576199">至开往古城站</d><d p="86.26500,1,25,16777215,1606230288,0,4340e07f,41464948736393219">笑死我了哈哈</d><d p="29.61000,1,25,16707842,1606007196,0,7fb9dd70,41347984305160195">？？？？</d><d p="58.08600,1,25,16777215,1605962252,0,19d79521,41324420909760515">牛逼，哈哈优秀</d><d p="4.27900,1,25,16777215,1605764827,0,2ff7bc68,41220913495539719">演技巅峰</d><d p="13.16200,1,25,16777215,1605103492,0,35c4af88,40874183246741511">红豆劲敌</d><d p="26.66000,1,25,38979,1605003916,0,bfb45699,40821976567119879">??????</d><d p="14.29900,1,25,16777215,1604840819,0,d0e8aae9,40736466965364739">入伏</d><d p="5.42600,1,25,14811775,1604840795,0,d0e8aae9,40736454168018951">结婚的哥我都没任何附加r分</d><d p="56.71400,1,25,16777215,1604809531,0,24633196,40720063274680323">哈哈哈哈</d><d p="85.41200,1,25,16777215,1604804645,0,ef111ec2,40717501406380039">ou la ou la lololololol</d><d p="75.17200,1,25,16777215,1604726135,0,5394aa7,40676339619463171">红红火火恍恍惚惚</d><d p="105.73900,1,25,16777215,1604716885,0,e887a881,40671489681260549">哈哈哈</d><d p="102.37000,1,25,16777215,1604640768,0,7afb11a0,40631582346706951">？？？？？</d><d p="94.13000,1,25,16777215,1604640746,0,7afb11a0,40631571227607043">曹操的英文什么情况</d><d p="54.92000,1,25,16777215,1604146446,0,6bcd2c4f,40372415750995975">秀儿</d><d p="19.00000,1,25,16777215,1604146387,0,6bcd2c4f,40372384369213443">祖传开头</d><d p="84.99000,1,25,16777215,1604052159,0,ebb4ed5b,40322981937283079">？？？？？？？？？？？？？？</d><d p="36.14000,1,25,16777215,1603802404,0,2e3471d5,40192038541983749">NB </d><d p="77.67300,1,25,16777215,1603279713,0,4a97337,39917997787709447">哈哈哈哈哈哈哈哈哈哈</d><d p="12.36600,1,25,16777215,1602857568,0,30d6ab0a,39696672254066691">6</d><d p="106.55500,1,25,16777215,1602774865,0,ef18cca0,39653312248152071">哈哈哈哈哈哈哈哈</d><d p="88.21800,1,25,16777215,1602774847,0,ef18cca0,39653302630088711">俄语</d><d p="93.72100,1,25,16777215,1602759261,0,7c630b26,39645131004968967">害怕</d><d p="72.38200,1,25,16777215,1602599016,0,602f6863,39561116749135877">上瘾了</d><d p="19.98400,1,25,16777215,1602143472,0,a890774,39322280277835781">杨紫</d><d p="30.07900,1,25,16777215,1602135848,0,28c4343b,39318283194728451">▄▅▆▇█▇▆▅▄▄▅▆▇█▇▆▅▄▄▅▆▇█▇▆▅▄▄▅▆▇█▇▆▅▄▄▅▆▇█▇▆▅▄▄▅▆▇█▇▆▅▄▄▅▆▇█▇▆▅▄▄▅▆▇█▇▆▅▄▄▅▆▇█▇▆▄▄▅▄▄▄</d><d p="7.72400,1,25,16777215,1602135826,0,28c4343b,39318271500484611">▄▅▆▇█▇▆▅▄▄▅▆▇█▇▆▅▄▄▅▆▇█▇▆▅▄▄▅▆▇█▇▆▅▄▄▅▆▇█▇▆▅▄▄▅▆▇█▇▆▅▄▄▅▆▇█▇▆▅▄▄▅▆▇█▇▆▅▄▄▅▆▇█▇▆▄▄▅▆▇█▇▆▅▄▄▅▄▄▄</d><d p="43.48000,1,25,16777215,1602122974,0,8b4aa136,39311533387284487">绿的绿的</d><d p="73.62300,1,25,16777215,1602090070,0,54ba8afa,39294282057121795">哈哈哈哈</d><d p="83.48100,1,25,16777215,1602090021,0,54ba8afa,39294256692592647">哈哈哈</d><d p="78.62500,1,25,16777215,1601960279,0,6aad509d,39226234301317127">仙走一步</d><d p="11.82500,1,25,16777215,1601947051,0,347a567f,39219299180085253">祖传开头</d><d p="47.47400,1,25,16777215,1601944876,0,caded56b,39218158908735493">虎狼之词</d><d p="8.47200,1,25,16777215,1601922557,0,caded56b,39206457088933895">祖传开头</d><d p="73.81200,1,25,16777215,1601880045,0,190fbe53,39184168614100995">1.25倍数新世界</d><d p="54.71700,1,25,16777215,1601786645,0,c619c997,39135200239157251">哈哈哈哈哈哈哈哈哈哈哈哈哈哈哈哈哈哈哈哈哈哈哈哈哈哈哈哈哈哈哈哈哈哈哈哈哈哈哈哈哈哈哈哈哈哈哈哈哈哈哈哈哈哈哈哈哈哈哈哈哈哈哈哈哈</d><d p="42.69600,1,25,16777215,1601785397,0,896e0682,39134545763631111">哈哈哈哈哈哈</d><d p="14.78200,1,25,16777215,1601087903,0,52d6a897,38768857853722629">祖传开头</d><d p="10.47200,1,25,16777215,1601051425,0,92a93736,38749732916953091">考古</d><d p="38.28000,1,25,15138834,1600694447,0,3c9caf61,38562573890617347">妙啊</d><d p="100.86400,1,25,16777215,1600525946,0,d75ad3fc,38474230551019527">？？？？？？？？？？？？？？</d><d p="27.71200,1,25,16777215,1600525828,0,9792a508,38474169077727235">？？？？</d><d p="80.65200,1,18,16777215,1600498845,0,7d45de2d,38460022275440647">哈哈哈</d><d p="74.82000,1,25,38979,1600488072,0,7d0f9d84,38454374132875271">绿色（shar）的帽子（zhi）</d><d p="27.67000,1,25,16777215,1600451262,0,ca24b987,38435074805334021">哈哈</d><d p="8.91700,1,25,16777215,1600322597,0,ed5b7b7e,38367617169227781">祖传开头</d><d p="26.71500,1,25,16777215,1600314319,0,31a2eaf8,38363277259964485">牛</d><d p="18.87000,1,25,16707842,1600261162,0,4cb338dd,38335407535423493">觉觉：啊，轻点～</d><d p="93.06800,1,25,16777215,1600220336,0,94071fe6,38314003253428231">曹操：wdnmd</d><d p="10.92500,1,25,16777215,1600144735,0,54b1ee1e,38274366676926469">可以可以</d><d p="104.38000,1,25,16707842,1600079532,0,5835cf00,38240181176762375">▄▅▆▇█▇▆▅▄▄▅▆▇█▇▆▅▄▄▅▆▇█▇▆▅▄▄▅▆▇█▇▆▅▄▄▅▆▇█▇▆▅▄▄▅▆▇█▇▆▅▄▄▅▆▇█▇▆▅▄▄▅▆▇█▇▆▅▄▄▅▆</d><d p="100.08000,1,25,16777215,1600079521,0,5835cf00,38240175551676423">▄▅▆▇█▇▆▅▄▄▅▆▇█▇▆▅▄▄▅▆▇█▇▆▅▄▄▅▆▇█▇▆▅▄▄▅▆▇█▇▆▅▄▄▅▆▇█▇▆▅▄▄▅▆▇█▇▆▅▄▄▅▆▇█▇▆▅▄▄▅▆</d><d p="63.18000,1,25,16777215,1600079482,0,5835cf00,38240155040481285">哈哈哈哈哈哈哈哈哈哈哈哈哈哈哈哈哈哈哈哈哈哈哈哈哈哈哈哈哈哈哈哈哈哈哈哈哈哈哈哈哈哈哈哈哈哈哈哈哈哈哈哈哈哈哈哈哈哈哈哈哈哈哈哈哈哈哈哈哈哈哈哈哈哈哈哈哈哈哈哈哈哈哈哈哈哈哈哈哈哈哈哈哈哈哈哈哈哈呵呵</d><d p="41.73900,1,25,16777215,1600079438,0,5835cf00,38240132082958339">■■■■囍╋╋╋╋</d><d p="103.55800,1,25,2236962,1600070335,0,761995b9,38235359385485315">⎛⎝≥⏝⏝≤⎠⎞    ⎛⎝≥⏝⏝≤⎠⎞    ⎛⎝≥⏝⏝≤⎠⎞    ⎛⎝≥⏝⏝≤⎠⎞   ⎛⎝≥⏝⏝≤⎠⎞  ⎛⎝≥⏝⏝≤⎠⎞    ⎛⎝≥⏝⏝≤⎠⎞    ⎛⎝≥⏝⏝≤⎠⎞   ⎛⎝≥⏝⏝≤⎠⎞</d><d p="96.27800,1,25,16740868,1600070328,0,761995b9,38235355534589957">⎛⎝≥⏝⏝≤⎠⎞    ⎛⎝≥⏝⏝≤⎠⎞    ⎛⎝≥⏝⏝≤⎠⎞    ⎛⎝≥⏝⏝≤⎠⎞   ⎛⎝≥⏝⏝≤⎠⎞  ⎛⎝≥⏝⏝≤⎠⎞    ⎛⎝≥⏝⏝≤⎠⎞    ⎛⎝≥⏝⏝≤⎠⎞   ⎛⎝≥⏝⏝≤⎠⎞</d><d p="89.22100,1,25,10546688,1600070321,0,761995b9,38235351881875463">⎛⎝≥⏝⏝≤⎠⎞    ⎛⎝≥⏝⏝≤⎠⎞    ⎛⎝≥⏝⏝≤⎠⎞    ⎛⎝≥⏝⏝≤⎠⎞   ⎛⎝≥⏝⏝≤⎠⎞  ⎛⎝≥⏝⏝≤⎠⎞    ⎛⎝≥⏝⏝≤⎠⎞    ⎛⎝≥⏝⏝≤⎠⎞   ⎛⎝≥⏝⏝≤⎠⎞</d><d p="80.60000,1,25,13369971,1600070312,0,761995b9,38235347315326981">⎛⎝≥⏝⏝≤⎠⎞    ⎛⎝≥⏝⏝≤⎠⎞    ⎛⎝≥⏝⏝≤⎠⎞    ⎛⎝≥⏝⏝≤⎠⎞   ⎛⎝≥⏝⏝≤⎠⎞  ⎛⎝≥⏝⏝≤⎠⎞    ⎛⎝≥⏝⏝≤⎠⎞    ⎛⎝≥⏝⏝≤⎠⎞   ⎛⎝≥⏝⏝≤⎠⎞</d><d p="71.77800,1,25,16777215,1600070303,0,761995b9,38235342726234115">⎛⎝≥⏝⏝≤⎠⎞    ⎛⎝≥⏝⏝≤⎠⎞    ⎛⎝≥⏝⏝≤⎠⎞    ⎛⎝≥⏝⏝≤⎠⎞   ⎛⎝≥⏝⏝≤⎠⎞  ⎛⎝≥⏝⏝≤⎠⎞    ⎛⎝≥⏝⏝≤⎠⎞    ⎛⎝≥⏝⏝≤⎠⎞   ⎛⎝≥⏝⏝≤⎠⎞</d><d p="42.02700,1,25,16777215,1600048651,0,f83b87b0,38223990918479877">哈哈哈哈哈哈哈</d><d p="60.46500,1,25,16776960,1600002484,0,38b4787a,38199785882648581">？？？？？？？？</d><d p="25.46800,1,25,9487136,1599982083,0,f22aa5dd,38189089937686533">6</d><d p="32.26200,1,25,16777215,1599958731,0,bac20805,38176846961967111">优秀啊</d><d p="47.35600,1,25,16777215,1599934299,0,f7bf1e6e,38164037235113991">哈哈哈哈哈哈</d><d p="61.35800,1,25,16777215,1599813312,0,f83b87b0,38100605161963525">哈哈哈哈哈哈</d><d p="44.80200,1,25,16777215,1599212813,0,e340eb05,37785771017502725">哈哈哈哈哈</d><d p="109.00000,1,25,16777215,1599136239,0,4c1fb433,37745624291475459">你币有了</d><d p="15.02000,1,25,16777215,1598964162,0,e974daf7,37655406297219079">杨紫杨紫杨紫杨紫杨紫杨紫杨紫杨紫杨紫杨紫杨紫</d><d p="8.09300,1,25,16777215,1598958022,0,b3a24b90,37652186861142023">祖传开头</d><d p="108.99200,1,25,16777215,1598863765,0,eec1a159,37602769186586631">w</d><d p="83.43400,1,25,52480,1598579319,0,8111d4b6,37453637385977859">⎛⎝≥⏝⏝≤⎠⎞    ⎛⎝≥⏝⏝≤⎠⎞    ⎛⎝≥⏝⏝≤⎠⎞    ⎛⎝≥⏝⏝≤⎠⎞    ⎛⎝≥⏝⏝≤⎠⎞   ⎛⎝≥⏝⏝≤⎠⎞⎛⎝≥⏝⏝≤⎠⎞    ⎛⎝≥⏝⏝≤⎠⎞    ⎛⎝≥⏝⏝≤⎠⎞</d><d p="21.91500,1,25,52480,1598579257,0,8111d4b6,37453605150130183">▄▅▆▇█▇▆▅▄▄▅▆▇█▇▆▅▄▄▅▆▇█▇▆▅▄▄▅▆▇█▇▆▅▄▄▅▆▇█▇▆▅▄▄▅▆▇█▇▆▅▄▄▅▆▇█▇▆▅▄▄▅▆▇█▇▆▅▄▄▅▆▇█▇▆▅▄▄▅▆▇█▇▆▅▄▄▅▆▇█▇▆▅</d><d p="26.81400,1,25,16777215,1598540667,0,f53e298,37433373027729413">厉害厉害</d><d p="1.46100,1,25,16777215,1598439395,0,85bc72c,37380277165621253">▄▅▆▇█▇▆▅▄▄▅▆▇█▇▆▅▄▄▅▆▇█▇▆▅▄▄▅▆▇█▇▆▅▄▄▅▆▇█▇▆▅▄▄▅▆▇█▇▆▅▄▄▅▆▇█▇▆▅▄▄▅▆▇█▇▆▅▄▄▅▆▇█▇▆▅▄▄▅▆▇█▇▆▅▄▄▅▆▇█▇▆▅</d><d p="61.74200,1,25,16777215,1598416910,0,5ed57f59,37368488687828995">杨紫张一山黑历史</d><d p="15.19400,1,25,16777215,1598361701,0,e425e55d,37339543310434307">我的手机在震</d><d p="42.76400,1,25,16777215,1598317262,0,8de28f6a,37316244499595267">看一遍，笑一遍</d><d p="5.43800,1,25,16777215,1598274099,0,826fa486,37293614582202375">祖传开头</d><d p="99.62400,1,25,16777215,1598191103,0,92649a0a,37250100884930567">(づ ●─● )づ(づ ●─● )づ(づ ●─● )づ(づ ●─● )づ(づ ●─● )づ(づ ●─● )づ(づ ●─● )づ(づ ●─● )づ(づ ●─● )づ(づ ●─● )づ</d><d p="51.03900,1,25,16777215,1598064198,0,3839fb08,37183565690044421">哈哈哈哈哈哈哈哈哈哈哈哈哈哈哈哈哈哈哈哈哈哈哈哈哈哈哈哈哈哈哈哈哈哈哈哈哈哈哈哈哈哈哈哈哈哈哈哈哈哈哈哈哈哈哈哈哈哈哈哈哈哈哈哈</d><d p="51.76700,1,25,16777215,1597998906,0,646e93fc,37149333946630147">哈哈哈哈哈哈哈哈哈哈或或或或</d><d p="30.24800,1,25,41194,1597905905,0,b46210d9,37100574850678789">我都忘了原声了</d><d p="79.62700,1,25,16646914,1597754585,0,6feeff5c,37021239242915845">woc</d><d p="61.60800,1,25,16646914,1597754566,0,6feeff5c,37021229821460487">哈哈哈哈哈哈哈哈哈哈哈哈哈哈哈哈哈哈哈哈哈哈哈哈哈哈哈哈哈哈哈哈哈哈哈哈哈哈哈哈哈哈哈哈哈哈哈哈哈哈哈哈哈哈哈哈哈哈</d><d p="26.81400,1,25,16777215,1597754532,0,6feeff5c,37021211611365379">火钳刘明</d><d p="10.48600,1,25,16777215,1597754493,0,7792082f,37021191393247237">1</d><d p="7.74400,1,25,16777215,1597691472,0,3769972a,36988149900509187">？？？？？？？？？？？？？？？？？？？？？？？？？？？？？？？？？？？？？？？？？？？？？？？？？？？？？？？？？？？？？？？？？？？？？？？？？？？？？？？</d><d p="12.59900,1,25,16777215,1597548750,0,f594dab7,36913322803593223">哈哈</d><d p="4.96000,1,25,16777215,1597505680,0,b70f86d6,36890741453094919">祖传开头</d><d p="31.32400,1,25,16776960,1597502944,0,33974ef1,36889307036254213">yellow？</d><d p="103.26500,1,25,16777215,1597492611,0,a2f82281,36883889394810885">哈哈哈哈哈哈哈哈</d><d p="96.90400,1,25,16777215,1597492604,0,a2f82281,36883886101233671">老太太钻被窝</d><d p="80.23100,1,25,16777215,1597492588,0,a2f82281,36883877317836805">？？？？</d><d p="74.95000,1,25,16777215,1597492582,0,a2f82281,36883874587869191">哈哈哈哈哈哈</d><d p="64.66700,1,25,16777215,1597492572,0,a2f82281,36883869195042819">哈哈哈哈</d><d p="55.06100,1,25,16777215,1597492562,0,a2f82281,36883864167120903">哈哈哈哈华华姐</d><d p="47.34800,1,25,16777215,1597492555,0,a2f82281,36883860104413187">是</d><d p="40.55700,1,25,16777215,1597492548,0,a2f82281,36883856539779075">？？？？？</d><d p="30.83600,1,25,16777215,1597492538,0,a2f82281,36883851438456835">？？？？？</d><d p="19.74300,1,25,16777215,1597492527,0,a2f82281,36883845633015811">哈哈哈哈</d><d p="85.41800,1,25,16777215,1597470290,0,781362a5,36872187203289091">牛逼</d><d p="108.99200,1,25,52480,1597459929,0,e7cf8fcb,36866755127148551">哈哈哈哈哈哈哈哈哈哈哈哈哈哈哈哈哈哈哈哈哈哈哈哈哈哈哈哈哈哈哈哈哈哈哈哈哈哈哈哈哈哈哈哈哈哈哈哈哈哈哈哈哈哈哈哈哈哈哈哈哈哈哈哈</d><d p="95.85800,1,25,52480,1597459916,0,e7cf8fcb,36866748052930563">。。。。。。。。。。。。。。。。。。。。。。。。。。。。。。。。。。。。。。。。。。。。。。。。。。。。。。。。。。。。。。。。。。。。。。。。。。。。。。。。。。。。。。。。。。。。。。。。。。。。</d><d p="66.18200,1,25,52480,1597459886,0,e7cf8fcb,36866732477382659">？？？？？？？？？？？？？？？？？？？？？？？？？？？？？？？？？？？？？？？？？？？？？？？？？？？？？？？？？？？？？？？？？？？？？？？？？？？？？？？？？？？？？？？？？？？？？？？？？？？？</d><d p="70.19400,1,25,16777215,1597459834,0,e7cf8fcb,36866704983719939">哈哈哈哈哈哈哈哈哈哈哈哈哈哈哈哈哈哈哈哈哈哈哈哈哈哈哈哈哈哈哈哈哈哈哈哈哈哈哈哈哈哈哈哈哈哈哈哈哈哈哈哈哈哈哈哈哈哈哈哈哈哈哈哈哈哈哈哈哈哈哈哈哈哈哈哈哈哈哈哈哈哈哈哈哈哈哈哈哈哈哈哈哈哈哈哈哈哈哈哈</d><d p="61.40500,1,25,16777215,1597441223,0,6195a56a,36856947581911043">山哥紫妹太好玩了</d><d p="45.69600,1,25,16777215,1597386137,0,a41dcc9d,36828066497429511">绿的</d><d p="108.07800,1,25,16777215,1597253269,0,9d15167a,36758405483331589">染成绿哈哈哈哈笑死了</d><d p="68.83900,1,25,16777215,1597253184,0,9d15167a,36758361150062599">恐怖奶奶可还行</d><d p="7.32800,1,25,16777215,1597221927,0,a43a51de,36741973022343173">▁▃▅▇█▇▅▃▁▁▃▅▇█▇▅▃▁▁▃▅▇█▇▅▃▁▁▃▅▇█▇▅▃▁▁▃▅▇█▇▅▃▁▁▃▅▇█▇▅▃▁▁▃▅▇█▇▅▃▁▁▃▅▇█▇▅▃▁▁▃▅▇█▇▅▃▁▁▃▅▇█▇▅▃</d><d p="25.93200,1,25,16777215,1597208311,0,ce93e1cf,36734834503581699">凌潇肃</d><d p="70.99500,1,25,16777215,1597130182,0,8a4ede4a,36693872534880261">刘星是gay</d><d p="67.02700,1,25,16646914,1597048042,0,526ef1d1,36650807251697669">ohhhhhhhhhhhhhhhhhhhhhhhhhhhhhhhhhhhhhhhhhhhhhhhhhhhhhhhhhhhhhhh</d><d p="34.50100,1,25,52480,1597048009,0,526ef1d1,36650790213910535">哈哈哈哈哈哈哈哈哈哈哈哈哈哈哈哈哈哈哈哈哈哈哈哈哈哈哈哈哈哈哈哈哈哈哈哈哈哈哈哈哈哈哈哈哈哈哈哈哈哈哈哈哈哈哈哈哈哈哈哈哈哈哈哈</d><d p="78.70900,1,25,16777215,1597028896,0,2fe2f666,36640769324351495">已笑死</d><d p="31.61500,1,25,16777215,1597020312,0,e7cf8fcb,36636269184286727">秀儿</d><d p="8.27000,1,25,16776960,1596970160,0,dd647293,36609974750150663">呵呵呵呵呵呵呵呵呵呵呵呵呵呵呵呵呵呵呵呵呵呵呵呵呵呵呵呵呵呵呵呵呵呵呵呵呵呵呵呵呵呵呵呵呵呵呵呵呵呵呵呵呵呵呵呵呵呵呵呵呵呵呵呵呵呵呵呵呵呵呵呵呵呵呵呵呵呵呵呵呵呵呵呵呵呵呵呵呵呵呵呵呵呵呵呵呵呵呵呵</d><d p="77.54000,1,25,16776960,1596970123,0,dd647293,36609955442196483">呵呵呵呵呵呵呵呵呵呵呵呵呵呵呵呵呵呵呵呵呵呵呵呵呵呵呵呵呵呵呵呵呵呵呵呵呵呵呵呵呵呵呵呵呵呵呵呵呵呵呵呵呵呵呵呵呵呵呵呵呵呵呵呵</d><d p="70.06300,1,25,52480,1596952097,0,a9135c83,36600504446353411">哈哈哈哈哈哈哈哈哈哈哈哈哈哈哈哈哈哈哈哈哈哈哈哈哈哈哈哈哈哈哈哈哈哈哈哈哈哈哈哈哈</d><d p="62.56200,1,25,16777215,1596945245,0,f8fda4d0,36596912211099655">红红火火恍恍惚惚</d><d p="94.60900,1,25,16777215,1596935351,0,e1dd5b6c,36591725172490245">梅开二度</d><d p="61.79700,1,25,16777215,1596907527,0,b97a99d1,36577137189715971">哈哈哈</d><d p="56.44000,1,25,16777215,1596907522,0,b97a99d1,36577134359609347">太带感了</d><d p="64.39300,1,25,16777215,1596888433,0,3840b0fa,36567126465052677">恐怖奶奶</d><d p="11.54500,1,25,16777215,1596872208,0,11d70995,36558619708227589">来啦</d><d p="33.09700,1,25,16646914,1596866700,0,6917c84d,36555731931496453">⎛⎝≥⏝⏝≤⎠⎞    ⎛⎝≥⏝⏝≤⎠⎞    ⎛⎝≥⏝⏝≤⎠⎞    ⎛⎝≥⏝⏝≤⎠⎞    ⎛⎝≥⏝⏝≤⎠⎞   ⎛⎝≥⏝⏝≤⎠⎞⎛⎝≥⏝⏝≤⎠⎞    ⎛⎝≥⏝⏝≤⎠⎞    ⎛⎝≥⏝⏝≤⎠⎞</d><d p="15.23200,1,25,16777215,1596866680,0,6917c84d,36555721533816839">⎛⎝≥⏝⏝≤⎠⎞    ⎛⎝≥⏝⏝≤⎠⎞    ⎛⎝≥⏝⏝≤⎠⎞    ⎛⎝≥⏝⏝≤⎠⎞    ⎛⎝≥⏝⏝≤⎠⎞   ⎛⎝≥⏝⏝≤⎠⎞⎛⎝≥⏝⏝≤⎠⎞    ⎛⎝≥⏝⏝≤⎠⎞    ⎛⎝≥⏝⏝≤⎠⎞</d><d p="56.70900,1,18,15138834,1596825026,0,58b2d1ea,36533882842513411">哈哈哈哈哈哈哈哈哈</d><d p="104.50300,1,25,16777215,1596746883,0,6195a56a,36492913598791685">哈哈哈哈哈哈哈</d><d p="58.00100,1,25,16777215,1596746837,0,6195a56a,36492889260818439">哈哈哈哈哈哈哈</d><d p="78.02000,1,25,16777215,1596645387,0,b34c78d,36439700088029187">我选择死亡</d><d p="23.94300,1,25,16777215,1596625705,0,f53e298,36429381316378629">厉害厉害</d><d p="35.36600,1,25,52480,1596553484,0,33390eda,36391516744187907">原谅色</d><d p="34.70000,1,25,16777215,1596533780,0,9317e740,36381186011955205">妙啊</d><d p="93.09200,1,25,16777215,1596517763,0,f0b70a1b,36372788523565059">哈哈哈哈哈哈哈</d><d p="86.44000,1,25,16777215,1596517756,0,f0b70a1b,36372785036525571">哈哈哈哈哈哈哈</d><d p="81.95700,1,25,16777215,1596517752,0,f0b70a1b,36372782662025221">哈哈哈哈哈哈哈</d><d p="78.09900,1,25,16777215,1596517748,0,f0b70a1b,36372780653477891">哈哈哈哈哈哈哈</d><d p="73.06400,1,25,16777215,1596517743,0,f0b70a1b,36372778005823493">哈哈哈哈哈哈哈</d><d p="9.79200,1,25,16777215,1596510229,0,edd6c04e,36368838458605573">祖传开头</d><d p="75.52000,1,25,16777215,1596463569,0,ede0610c,36344375526555651">？？？？？？？</d><d p="60.79900,1,25,16777215,1596448963,0,d1b3b49a,36336717416366087">老太太钻被窝哈哈哈哈哈哈哈哈哈哈哈</d><d p="52.27900,1,25,16777215,1596448942,0,d1b3b49a,36336706463989767">百万配音</d><d p="43.85200,1,25,16707842,1596442446,0,53eb4fa8,36333300555448327">你币有了★</d><d p="58.81900,1,25,16777215,1596437160,0,2ae7a794,36330529596375045">哈哈哈哈哈</d><d p="52.02000,1,25,16777215,1596433682,0,8a6f785f,36328705647181829">绿色</d><d p="9.58900,1,25,16777215,1596389451,0,d6c6dda9,36305516022464515">请保护好自己</d><d p="76.39000,1,25,16777215,1596288734,0,7e0e6873,36252711612055557">n</d><d p="58.86100,1,25,16777215,1596274022,0,74404ec4,36244997957746693">牛皮！</d><d p="91.60900,1,25,16777215,1596259987,0,ff31436,36237639731904519">哈哈哈哈哈哈哈哈哈</d><d p="59.66400,1,25,16777215,1596259955,0,ff31436,36237622974611463">哈哈哈哈哈哈</d><d p="91.20800,1,25,16777215,1596171365,0,84275c8d,36191175986118659">勤快点打我</d><d p="4.24800,1,25,16777215,1596171265,0,84275c8d,36191123738722309">祖传开头</d><d p="103.82600,1,25,16777215,1596124644,0,fc422319,36166680795152389">文化文化</d><d p="27.74200,1,25,16777215,1596119221,0,520234d0,36163837545152519">哈哈哈哈h</d><d p="20.09700,1,25,16777215,1596010862,0,d3ea81ca,36107026590334979">hhhhhhhhhhhhhhhhh</d><d p="37.60900,1,25,16777215,1595954325,0,1e64c2d2,36077384640757765">自己的颜色</d><d p="28.10000,1,25,16777215,1595953969,0,a92b3ba5,36077198195032071">wdnmd好听</d><d p="48.24900,1,25,16777215,1595914335,0,1a7bc8a9,36056418229420101">这个夏雪真的很美</d><d p="45.81000,1,25,16777215,1595914256,0,1a7bc8a9,36056377257361415">这个夏雪真的很美哎</d><d p="58.01900,1,25,16777215,1595908708,0,f90407a,36053468374892551">红红火火恍恍惚惚哈哈哈哈哈哈</d><d p="71.66400,1,25,16777215,1595894432,0,1cbfb2a3,36045983807176711">O(∩_∩)O哈哈~</d><d p="93.40600,1,25,16777215,1595817097,0,24c54fc4,36005437555867655">f*ck是什么鬼</d><d p="11.77100,1,25,16777215,1595816753,0,10ffe7f9,36005257317711879">祖传开头</d><d p="84.61800,1,25,16777215,1595424027,0,78c06673,35799355972124679">不知道张一山看了会怎么样，嘻嘻嘻</d><d p="61.76100,1,25,16777215,1595423965,0,78c06673,35799323126530055">老太太钻被喔</d><d p="31.68200,1,25,16777215,1595423895,0,78c06673,35799286808576003">她的青春是绿色的</d><d p="104.06500,1,25,16777215,1595423558,0,3c7dbc38,35799109762285571">英语好评</d><d p="54.91600,1,25,16777215,1595422713,0,7cd173ff,35798667009982467">哈哈哈哈哈哈</d><d p="5.34000,1,25,16777215,1595418361,0,7e0641f,35796385302315011">祖传开头</d><d p="65.08200,1,25,16777215,1595387594,0,7a50ab56,35780254730027011">哈哈哈哈哈哈哈哈哈哈哈哈哈哈哈哈哈哈哈</d><d p="108.38500,1,25,16707842,1595387532,0,dc1b9585,35780221804216323">？？？？？？</d><d p="91.94800,1,25,16707842,1595387508,0,dc1b9585,35780209361289285">英文字幕？？？</d><d p="67.70000,1,25,16777215,1595350084,0,d726dc81,35760588301271043">仙走一步</d><d p="58.94400,1,25,16776960,1595338207,0,42546cc4,35754361303334915">老太太钻被窝</d><d p="46.41000,1,25,52480,1595338155,0,42546cc4,35754334293065733">?????</d><d p="62.14000,1,25,9487136,1595337317,0,98ce2a53,35753895079182339">老太太钻被窝，我变色了。</d><d p="35.99100,1,25,38979,1595337283,0,98ce2a53,35753876909981703">？？</d><d p="4.45700,1,25,16777215,1595337250,0,98ce2a53,35753859801415683">祖传开头。</d><d p="57.85400,1,25,16777215,1595238531,0,24ec912c,35702102536749059">哈哈哈哈哈哈哈好好</d><d p="31.31200,1,25,16777215,1595238504,0,24ec912c,35702088611135493">哈哈哈哈哈</d><d p="19.93400,1,25,16777215,1595171601,0,4e88ee36,35667011966074887">有才啊</d><d p="84.69900,1,25,16777215,1595165627,0,3b27a4b8,35663879937196037">𝗙𝗕𝗜! 𝗢𝗽𝗲𝗻 𝗧𝗵𝗲 𝗗𝗼𝗼𝗿!</d><d p="11.38300,1,25,16777215,1595156781,0,440fae72,35659241836511239">祖传开头</d><d p="107.84000,1,25,16777215,1595090588,0,8b7d66d2,35624537587449859">你说的好有道理，我竟然无力反驳。</d><d p="5.59000,1,25,16777215,1595079789,0,8eb4078c,35618876018393093">一天一遍，欢乐无限</d><d p="2.84100,1,25,16777215,1595035388,0,fde7c3a,35595596912394247">.</d><d p="96.86900,1,25,16777215,1594974057,0,2bab9ae0,35563441886855175">Kagura Mea,up老财布了</d><d p="33.71000,1,25,16777215,1594902293,0,a73c4432,35525816916377605">魔性</d><d p="17.79800,1,25,16777215,1594902254,0,a73c4432,35525796508991495">？？？？？？？？？？？？？？？？？？？？？？？？？？？？？？？？？？？？？？？？？？？？？？？？？？？？？？？？？？？？？？？</d><d p="103.93100,1,25,16777215,1594820952,0,ab21c144,35483170671427591">你币没了</d><d p="66.30500,1,25,16777215,1594714238,0,8bbcaa34,35427222144679943">2020 7 14</d><d p="41.47300,1,25,16777215,1594714213,0,8bbcaa34,35427209108258823">2020     7  13</d><d p="14.02200,1,25,16777215,1594714186,0,8bbcaa34,35427194730184707">2020</d><d p="89.74800,1,25,16777215,1594695752,0,18032f04,35417530241646599">秘籍:老太太钻被窝[滑稽]</d><d p="24.77400,1,25,16777215,1594622062,0,16cefd97,35378895196782599">hhh</d><d p="28.42600,1,25,16777215,1594526458,0,13691ea8,35328771137470469">哇⊙∀⊙！这播放量</d><d p="105.99400,1,25,16777215,1594490957,0,b37a1cac,35310158576353285">？？？？？？？？？？？？？？？？？？？？？？？？？？？？？？？？？？？？？？？？？？？？？？？？？？？？？？？？？？？？？？？？？？？？？？？？？？？？？？？？？？？？？？？？？？？？？？？？？？？？</d><d p="50.99800,1,25,16777215,1594484297,0,3b9795fd,35306666522574851">哈哈哈哈哈哈哈哈哈哈哈哈哈哈哈哈哈哈哈哈哈哈</d><d p="35.18900,1,25,16707842,1594293837,0,c7ae8ab6,35206811085176837">？？？</d><d p="22.96300,1,25,16707842,1594293825,0,c7ae8ab6,35206804661075973">？？？？</d><d p="5.99200,1,25,16777215,1594269749,0,4daa5daa,35194181538807811">笑死人不偿命</d><d p="109.00000,1,25,16777215,1594269733,0,4daa5daa,35194173642506247">笑死人不偿命</d><d p="81.88100,1,25,16777215,1594130399,0,27ac536c,35121122218344451">达瓦里氏！伏特加！！！！</d><d p="92.55900,1,25,16777215,1594103140,0,adbf856d,35106830871429127">黄色青春</d><d p="48.00500,1,25,16777215,1594103096,0,adbf856d,35106807504437251">搞颜色</d><d p="21.85700,1,25,16777215,1594103050,0,adbf856d,35106783289671687">生物课上搞颜色</d><d p="8.59000,1,25,16777215,1594103017,0,adbf856d,35106766338916357">欧耶</d><d p="91.39500,1,25,16777215,1594025866,0,eae06c0,35066316761071685">。0  。</d><d p="42.11800,1,25,16777215,1594025817,0,eae06c0,35066290967674887">6 6 6</d><d p="64.78800,1,25,16777215,1593951396,0,b51e5890,35027273300049925">哈哈哈哈哈哈哈哈哈哈哈哈</d><d p="78.05500,1,25,16776960,1593946685,0,60084373,35024803002318853">y***** again</d><d p="29.11500,1,25,16776960,1593946610,0,60084373,35024763772469251">嗯，我也有</d><d p="55.45900,1,25,16777215,1593944521,0,46f6a0ea,35023668830011399">笑死我了</d><d p="24.63500,1,25,16777215,1593915278,0,54a00b51,35008336693821445">祖传开头</d><d p="71.89100,1,25,16777215,1593879854,0,54fc637b,34989764427382787">淦淦淦淦淦淦淦淦淦淦淦淦淦淦淦淦淦淦淦淦</d><d p="20.24600,1,25,16776960,1593877948,0,ea1eb186,34988765349412867">？？？？</d><d p="61.14900,1,25,16777215,1593864178,0,2cc6eded,34981545808232451">我使用双节棍去打奶奶？？？？？？？</d><d p="80.37800,1,25,16777215,1593841784,0,6b399dfe,34969805052182533">哈哈哈哈哈弹幕一遍，英文一遍，中文一遍，哈哈哈哈哈哈哈哈哈</d><d p="78.76900,1,25,16777215,1593841644,0,6b399dfe,34969731593142279">哈哈哈哈哈哈</d><d p="7.27000,1,25,16777215,1593841573,0,6b399dfe,34969694254923783">哈哈哈哈哈哈哈哈哈哈哈</d><d p="96.83800,1,25,16777215,1593841415,0,6b399dfe,34969611179393029">哈哈哈哈哈哈哈哈哈哈哈哈哈</d><d p="58.83900,1,25,16777215,1593841376,0,6b399dfe,34969591119609863">哈哈哈哈哈哈哈哈哈哈哈哈哈哈哈</d><d p="26.83800,1,25,16777215,1593841344,0,6b399dfe,34969574393249797">哈哈哈哈哈哈哈哈哈哈哈哈</d><d p="45.10000,1,25,16777215,1593761158,0,1577b562,34927533855080453">哈哈哈</d><d p="18.64000,1,25,16777215,1593680066,0,1566c00c,34885018303070211">祖传开头呢</d><d p="10.66600,1,25,16777215,1593669599,0,3b3002b7,34879530247127045">祖传开头</d><d p="29.11600,1,25,15772458,1593611855,0,781678b2,34849255850508293">注意英文</d><d p="26.30200,1,25,16777215,1593413099,0,ebc6ff3e,34745050470547459">？？？</d><d p="42.44000,1,25,16777215,1593364521,0,e1056f7,34719581375299591">再来亿遍</d><d p="34.03800,1,25,38979,1593330463,0,f6afaf20,34701725400563719">绿</d><d p="13.22000,1,25,38979,1593168584,0,7dbf8006,34616854378446851">祖传</d><d p="32.11700,1,25,16777215,1593142859,0,7985427a,34603367045529605">哈哈哈哈哈哈哈哈哈哈笑死了</d><d p="12.91700,1,25,16777215,1592911896,0,1af4d980,34482275874242565">再来一遍</d><d p="37.18200,1,25,16777215,1592883771,0,78d5fad8,34467530024681477">卧槽牛逼</d><d p="93.60400,1,25,16777215,1592766356,0,ded297ae,34405970795823111">你币有了哈哈哈</d><d p="47.60400,1,25,16777215,1592766310,0,ded297ae,34405946626670599">哈哈哈哈哈</d><d p="62.21800,1,25,16777215,1592666440,0,68b3170,34353586056462343">哈哈哈</d><d p="63.24000,1,25,16777215,1592657477,0,76ec2ac5,34348886782902275">杀马特</d><d p="54.29200,1,18,9487136,1592632853,0,ce94c81a,34335977053356035"> 绿 色 </d><d p="27.67400,1,25,16646914,1592138375,0,a2d01483,34076728126078981">要素过多</d><d p="5.71500,1,25,41194,1592135041,0,5d999d5f,34074979854188547">新冠考古</d><d p="1.00300,1,25,16777215,1592111845,0,726b2c44,34062818672115717">600万贺电</d><d p="108.49600,1,25,16777215,1592036579,0,d55cc229,34023357753589765">把男同学打掉</d><d p="86.53400,1,25,16777215,1592036557,0,d55cc229,34023346243371015">哈哈哈哈哈哈哈哈哈哈哈哈哈哈哈哈哈哈哈</d><d p="85.80700,1,25,16777215,1591940667,0,1605aabd,33973071801483269">p p p p p p p p p p p p p p p p p p</d><d p="75.56000,1,25,16776960,1591802467,0,f14957a5,33900615579467783">？？？？？？？？？？？？？？？？？？？？？？？？？？？？？？？？？？？？？？？？？？？？</d><d p="20.11500,1,25,16776960,1591802412,0,f14957a5,33900586503503875">？？？？？？？？？？？？</d><d p="8.44100,1,25,16777215,1591802267,0,f29a2afa,33900510322360323">祖传开头</d><d p="105.14000,1,25,16777215,1591797746,0,bc3f02eb,33898140515958789">这旋律可以啊！</d><d p="41.90000,1,25,16777215,1591693308,0,5ba9b67c,33843384887541765">其实你开了弹幕</d><d p="74.74900,1,25,16777215,1591619923,0,17e0e765,33804910000603141">开始吟唱</d><d p="42.61300,1,25,16777215,1591604198,0,ff2c5066,33796665415041029">你币有了</d><d p="48.50500,1,25,52480,1591499530,0,d4d5ddb5,33741789217161223">？？？？？？？？？？？？？？？？？？？？、</d><d p="6.88900,1,25,16777215,1591498998,0,54a4d399,33741510319538183">哈哈哈哈</d><d p="70.43900,1,25,16777215,1591456273,0,72f8e94,33719110258917443">鹅鹅鹅</d><d p="70.70900,1,25,4351678,1591452659,0,c244b4b7,33717215558631429">淦</d><d p="93.92000,1,25,16777215,1591424925,0,50019da4,33702674601869315">hhhhh</d><d p="88.67400,1,25,16777215,1591423770,0,e927c517,33702069243215875">hhh</d><d p="70.06300,1,25,41194,1591380768,0,9ceb9ecf,33679523602497543">哈哈哈哈哈哈哈哈哈哈哈哈</d><d p="7.65500,1,25,16777215,1591364568,0,2e6009de,33671030155771911">来了</d><d p="108.11600,1,25,16777215,1591361951,0,c87ada0a,33669657994985475">？？？？？？？？？？？？？？</d><d p="62.54300,1,25,16777215,1591361905,0,c87ada0a,33669634125201411">？？？？？？？？？？？？</d><d p="96.74200,1,25,38979,1591302005,0,e887a881,33638229388820487">哈哈哈</d><d p="64.81000,1,25,16777215,1591301973,0,e887a881,33638212695490567">逐渐忘了原唱</d><d p="109.00000,1,25,16777215,1591279303,0,917c78f8,33626326918758407">哈哈哈哈哈</d><d p="5.26000,1,25,16777215,1591239926,0,2e1c7e4c,33605681745494021">绿了开头</d><d p="24.56300,1,25,16777215,1591081847,0,4a8ec77a,33522803212812293">笑死人</d><d p="23.16900,1,25,16777215,1591002778,0,890c3f2f,33481347842965509">哈哈哈哈哈哈哈哈</d><d p="79.14200,1,25,16777215,1590986920,0,52fde86c,33473033675472901">哈哈哈</d><d p="22.17100,1,25,16777215,1590934601,0,be0af480,33445603609935879">淦</d><d p="43.31700,1,25,38979,1590908926,0,1e39b43f,33432142382366725">绿</d><d p="0.00000,1,25,52480,1590843984,0,d5cebfcb,33398094033321991">祖传开头</d><d p="99.89600,1,25,16777215,1590834436,0,5522ee4c,33393088428769287">哈哈哈哈哈哈哈哈哈哈哈哈哈哈哈哈哈哈哈哈</d><d p="40.00600,1,25,16777215,1590834376,0,5522ee4c,33393057094696963">哈哈哈哈哈哈哈哈哈哈哈</d><d p="8.87800,1,25,16777215,1590822760,0,ea6e2423,33386966627123205">▂▃▅▆▇▇▆▅▃▂▂▃▅▆▇▇▆▅▃▂▃▅▆▇▇▆▅▃▂▂▃▅▆▇▇▆▅▃▂▃▅▆▇▇▆▅▃▂▂▃▅▆▇▇▆▅▃▂▃▅▆▇▇▆▅▃▂▂▃▅▆▇▇▆▅▃▂▂▃▅▆▇▇▆▅▃▂▃▅▆▇▇▆▅▃▂</d><d p="29.02200,1,25,16777215,1590818429,0,82271ba8,33384696094130183">哈哈哈</d><d p="99.82000,1,25,16777215,1590814312,0,2a8d1b16,33382537640804359">⎛⎝≥⏝⏝≤⎠⎞    ⎛⎝≥⏝⏝≤⎠⎞    ⎛⎝≥⏝⏝≤⎠⎞    ⎛⎝≥⏝⏝≤⎠⎞    ⎛⎝≥⏝⏝≤⎠⎞   ⎛⎝≥⏝⏝≤⎠⎞</d><d p="88.98000,1,25,16777215,1590814290,0,2a8d1b16,33382526204510211">▄▅▆▇█▇▆▅▄▄▅▆▇█▇▆▅▄▄▅▆▇█▇▆▅▄▄▅▆▇█▇▆▅▄▄▅▆▇█▇▆▅▄▄▅▆▇█▇▆▅▄▄▅▆▇█▇▆▅▄▄▅▆▇█▇▆▅▄▄▅▆</d><d p="68.20000,1,25,16777215,1590761106,0,e16b2f93,33354642566414339">sucker?????</d><d p="47.57000,1,25,16777215,1590761076,0,e16b2f93,33354626552037381">英文好评</d><d p="73.73000,1,25,16777215,1590756375,0,6f9e4c56,33352162089631749">(　o=^•ェ•)o　┏━┓</d><d p="48.89800,1,25,16777215,1590727020,0,e887a881,33336771745415175">哈哈哈</d><d p="103.22000,1,25,16777215,1590673989,0,2a8d1b16,33308967794376711">⎛⎝≥⏝⏝≤⎠⎞    ⎛⎝≥⏝⏝≤⎠⎞    ⎛⎝≥⏝⏝≤⎠⎞    ⎛⎝≥⏝⏝≤⎠⎞    ⎛⎝≥⏝⏝≤⎠⎞   ⎛⎝≥⏝⏝≤⎠⎞</d><d p="50.23800,1,25,16777215,1590642698,0,40dc0d29,33292562605277187">哈哈哈哈哈哈哈</d><d p="15.91900,1,25,16777215,1590628458,0,50380be5,33285096472051717">考古尼玛呢？</d><d p="19.04800,1,25,16777215,1590550074,0,3c1bd4a3,33244000780550149">mm</d><d p="95.53700,1,25,16777215,1590499406,0,4856477d,33217436326035463">配绿的</d><d p="64.36400,1,25,16777215,1590499375,0,4856477d,33217419980308485">厉害了</d><d p="42.44700,1,25,16777215,1590499353,0,4856477d,33217408496828423">哈哈哈哈哈哈哈哈哈哈哈哈哈好好</d><d p="51.92300,1,25,16707842,1590495895,0,14b9b6e2,33215595372609543">哈哈哈哈</d><d p="104.25900,1,25,16777215,1590419515,0,f9e028d2,33175550345347075">哈哈哈哈哈哈哈哈哈哈哈哈哈哈</d><d p="55.25900,1,25,16777215,1590419466,0,f9e028d2,33175524642652163">哈哈哈哈哈哈哈哈哈去哈哈哈</d><d p="22.25800,1,25,16777215,1590419433,0,f9e028d2,33175507319652357">哈哈哈哈哈哈哈</d><d p="0.00000,1,25,15138834,1590392893,0,e956a079,33161592844058627">记得看底下的英语！！！！</d><d p="24.73400,1,25,52480,1590362640,0,dea4e3b3,33145731504668677">???</d><d p="44.89100,1,25,16777215,1590321439,0,b61dedab,33124130043199495">哈哈哈</d><d p="26.62900,1,25,16777215,1590321414,0,b61dedab,33124116952252421">？？</d><d p="24.32000,1,25,16777215,1590321405,0,b61dedab,33124112188047363">？？</d><d p="12.12100,1,25,16646914,1590311991,0,7604609a,33119176752627717">哈</d><d p="10.70600,1,25,16777215,1590211778,0,7270fd2e,33066636504727557">◤◢◤◢◤◢前方高能◤◢◤◢◤◢High energy ahead◤◢◤◢◤◢前方高能◤◢◤◢◤◢High energy ahead◤◢◤◢◤◢前方高能◤◢◤◢◤◢High energy ahead</d><d p="105.26500,1,25,52480,1590152966,0,b7435cdd,33035801662586887">绿的</d><d p="37.67800,1,25,16777215,1590145761,0,6915b23e,33032024530354181">？？？？？？？？</d><d p="68.20700,1,25,16777215,1590140769,0,99e79f98,33029406943870979">山东还没开学时代前来考古</d><d p="3.57900,1,25,16777215,1590129857,0,d24ee3ed,33023686139183109">赌船开头</d><d p="51.60100,1,25,16777215,1590128019,0,6552bf0e,33022722424963075">裂开WC</d><d p="87.60300,1,25,52480,1590053458,0,dea4e3b3,32983631078096899">靓仔</d><d p="4.41400,1,25,16777215,1589974376,0,db7a098a,32942169053986821">夏雪夏雨夏冰雹</d><d p="90.76500,1,25,16777215,1589961571,0,415cd91e,32935455712346119">欧拉欧拉you</d><d p="37.59400,1,25,38979,1589857514,0,a1e4ad6b,32880899937271811">你要的嘛</d><d p="19.15800,1,25,38979,1589857496,0,a1e4ad6b,32880890285129733">哈哈哈哈哈哈</d><d p="8.07500,1,25,16777215,1589857485,0,a1e4ad6b,32880884471824389">祖传开头</d><d p="6.24900,1,25,16777215,1589853480,0,112a7f19,32878785016627205">祖传开头</d><d p="51.70300,1,25,16777215,1589853244,0,112a7f19,32878661279940611">哈哈哈哈哈哈哈哈哈哈哈哈</d><d p="106.65500,1,25,16777215,1589802158,0,2fc6cdf9,32851877298700295">e......</d><d p="57.13800,1,25,16777215,1589696499,0,a26dda93,32796481707573251">弹幕</d><d p="108.99200,1,25,9033215,1589685700,0,4277be73,32790820070359047">⎛⎝≥⏝⏝≤⎠⎞    ⎛⎝≥⏝⏝≤⎠⎞    ⎛⎝≥⏝⏝≤⎠⎞    ⎛⎝≥⏝⏝≤⎠⎞    ⎛⎝≥⏝⏝≤⎠⎞   ⎛⎝≥⏝⏝≤⎠⎞</d><d p="30.83100,1,25,16777215,1589616824,0,4856477d,32754708806369283">灵性</d><d p="92.52400,1,25,16777215,1589499624,0,a22af279,32693262494990343">⎛⎝≥⏝⏝≤⎠⎞    ⎛⎝≥⏝⏝≤⎠⎞    ⎛⎝≥⏝⏝≤⎠⎞    ⎛⎝≥⏝⏝≤⎠⎞   ⎛⎝≥⏝⏝≤⎠</d><d p="90.43700,1,25,9599289,1589458686,0,a6868ddf,32671799194419203">卧槽</d><d p="66.12100,1,25,16777215,1589458011,0,e6b94756,32671445492957191">哈哈哈哈哈哈哈哈</d><d p="83.28100,1,25,16777215,1589447771,0,9f57d27,32666076705718279">⎛⎝≥⏝⏝≤⎠⎞    ⎛⎝≥⏝⏝≤⎠⎞    ⎛⎝≥⏝⏝≤⎠⎞    ⎛⎝≥⏝⏝≤⎠⎞    ⎛⎝≥⏝⏝≤⎠⎞   ⎛⎝≥⏝⏝≤⎠⎞</d><d p="42.37900,1,25,38979,1589415106,0,eebe5958,32648950841344003">哈哈哈</d><d p="42.37900,1,25,38979,1589415099,0,eebe5958,32648947057033219">哈哈哈哈哈哈哈哈</d><d p="68.44600,1,25,16777215,1589375266,0,13dc5c0b,32628063293931527">？？</d><d p="58.97900,1,25,16777215,1589375256,0,13dc5c0b,32628057692962819">？？？</d><d p="21.95700,1,25,16777215,1589353836,0,9763b359,32616827709292547">抖音已盗</d><d p="60.80300,1,25,16777215,1589327953,0,112a7f19,32603257191792643">？</d><d p="45.77200,1,25,16777215,1589327936,0,112a7f19,32603248451387395">绿</d><d p="34.04000,1,25,16777215,1589326869,0,112a7f19,32602689245806597">路的</d><d p="25.58800,1,25,16777215,1589274336,0,bf5342a7,32575146883547141">▅▆▇█▇▆▅▄▄▅▆▇█▇▆▄▄▅▆▇█▇▆▅▄▄▅▆▇█▇▆▅▄▄▅▆▇█▇▆▅▄▄▅▆▇█▇▆▅▄▄▅▆▇█▇▆▅▄▄▅▆▇█▇▆▅▄▄▅▆▇█▇▆▄▄▅▆█▇▆▅▄▅▆▇█▇▅▆▇█▇▆▅▄▄</d><d p="26.15700,1,25,15138834,1589264329,0,ca13f70b,32569900287393797">舒兰时代</d><d p="82.96900,1,25,16777215,1589252421,0,def63ee7,32563656900214787">⎛⎝≥⏝⏝≤⎠⎞    ⎛⎝≥⏝⏝≤⎠⎞    ⎛⎝≥⏝⏝≤⎠⎞    ⎛⎝≥⏝⏝≤⎠⎞    ⎛⎝≥⏝⏝≤⎠⎞</d><d p="77.62000,1,25,16777215,1589218104,0,fad06465,32545664741146627">哈哈哈哈</d><d p="91.51900,1,25,16777215,1589202090,0,afa5e4c5,32537268888010759">put your D in my va 这是什么虎狼之词</d><d p="97.99800,1,25,16777215,1589114935,0,b26d3758,32491574488203267">鬼畜成功</d><d p="77.07300,1,25,16777215,1589114914,0,b26d3758,32491563495981061">刘哦</d><d p="66.47100,1,25,16777215,1589114903,0,b26d3758,32491557972606979">？？？？？</d><d p="44.43400,1,25,9487136,1589040642,0,61c37e7b,32452623949365251">哈哈哈哈哈哈</d><d p="60.60300,1,25,16777215,1589030021,0,3614ef07,32447055109554181">\</d><d p="90.19600,1,25,408,1588998934,0,77ebd70f,32430756566401031">⎛⎝≥⏝⏝≤⎠⎞    ⎛⎝≥⏝⏝≤⎠⎞    ⎛⎝≥⏝⏝≤⎠⎞    ⎛⎝≥⏝⏝≤⎠⎞   ⎛⎝≥⏝⏝≤⎠⎞</d><d p="35.10000,1,25,52480,1588955548,0,687e6367,32408009818243141">罗          德           曼</d><d p="46.85800,1,25,52480,1588917375,0,1018c1e7,32387996068610053">？？？？？？</d><d p="41.97300,1,25,16777215,1588889549,0,8cbba1a6,32373407681609733">哈哈哈哈哈</d><d p="81.07300,1,25,16777215,1588848845,0,66a5533f,32352066816442373">⎛⎝≥⏝⏝≤⎠⎞    ⎛⎝≥⏝⏝≤⎠⎞    ⎛⎝≥⏝⏝≤⎠⎞    ⎛⎝≥⏝⏝≤⎠⎞    ⎛⎝≥⏝⏝≤⎠⎞   ⎛⎝≥⏝⏝≤⎠⎞</d><d p="78.69000,1,25,16707842,1588847312,0,b394f784,32351263187795973">▄▅▆▇█▇▆▅▄▄▅▆▇█▇▆▅▄▄▅▆▇█▇▆▅▄▄▅▆▇█▇▆▅▄▄▅▆▇█▇▆▅▄▄▅▆▇█▇▆▅▄▄▅▆▇█▇▆▅▄▄▅▆▇█▇▆▅▄▄▅▆▇█▇▆▄▄▅▆▇█▇▆▅▄▄▅▆▇█▇▆▅▄▄▅</d><d p="62.81900,1,25,16707842,1588847283,0,b394f784,32351247780544515">▄▅▆▇█▇▆▅▄▄▅▆▇█▇▆▅▄▄▅▆▇█▇▆▅▄▄▅▆▇█▇▆▅▄▄▅▆▇█▇▆▅▄▄▅▆▇█▇▆▅▄▄▅▆▇█▇▆▅▄▄▅▆▇█▇▆▅▄▄▅▆▇█▇▆▄▄▅▆▇█▇▆▅▄▄▅▆▇█▇▆▅▄</d><d p="100.63700,1,25,16777215,1588825897,0,e68d5f64,32340035580723203">日文字幕？</d><d p="26.10100,1,25,16777215,1588825823,0,e68d5f64,32339996510257155">英文字幕是认真的吗</d><d p="50.96200,1,25,16777215,1588741936,0,a945f539,32296015760457735">哈哈哈哈</d><d p="59.59400,1,25,16777215,1588739396,0,880d1c13,32294684208398339">？？？？？？？？？？？？？？？？</d><d p="5.13100,1,25,52480,1588669993,0,626922b0,32258296720654343">⎛⎝≥⏝⏝≤⎠⎞    ⎛⎝≥⏝⏝≤⎠⎞    ⎛⎝≥⏝⏝≤⎠⎞    ⎛⎝≥⏝⏝≤⎠⎞    ⎛⎝≥⏝⏝≤⎠⎞   ⎛⎝≥⏝⏝≤⎠⎞⎛⎝≥⏝⏝≤⎠⎞    ⎛⎝≥⏝⏝≤⎠⎞    ⎛⎝≥⏝⏝≤⎠⎞</d><d p="103.88700,1,25,16777215,1588669977,0,626922b0,32258288527081479">⎛⎝≥⏝⏝≤⎠⎞    ⎛⎝≥⏝⏝≤⎠⎞    ⎛⎝≥⏝⏝≤⎠⎞    ⎛⎝≥⏝⏝≤⎠⎞    ⎛⎝≥⏝⏝≤⎠⎞   ⎛⎝≥⏝⏝≤⎠⎞⎛⎝≥⏝⏝≤⎠⎞    ⎛⎝≥⏝⏝≤⎠⎞    ⎛⎝≥⏝⏝≤⎠⎞</d><d p="42.79900,1,25,16777215,1588669617,0,95c2e17c,32258099524927495">都是虎狼之词哈哈哈哈</d><d p="97.71200,1,25,16777215,1588666170,0,155789e3,32256292409573381">⎛⎝≥⏝⏝≤⎠⎞    ⎛⎝≥⏝⏝≤⎠⎞    ⎛⎝≥⏝⏝≤⎠⎞    ⎛⎝≥⏝⏝≤⎠⎞   ⎛⎝≥⏝⏝≤⎠</d><d p="13.47900,1,25,16777215,1588657532,0,e887a881,32251763809058821">不知道看了多少遍</d><d p="2.01200,1,25,16777215,1588595615,0,50050187,32219301310103557">多人运动时代考古</d><d p="69.69700,1,25,16777215,1588583060,0,cdc36f0a,32212718806106117">哈哈</d><d p="38.53700,1,25,16777215,1588583021,0,cdc36f0a,32212698769915911">胖</d><d p="5.09700,1,25,16777215,1588582951,0,cdc36f0a,32212662067134467">祖传开头又开始了</d><d p="53.28300,1,25,16777215,1588579250,0,d2ee02ba,32210721726529543">哈哈哈哈哈哈哈哈哈哈哈哈哈哈哈哈哈哈哈</d><d p="37.26800,1,25,16777215,1588579235,0,d2ee02ba,32210713396641799">哈哈哈哈哈哈哈哈哈哈哈哈哈哈哈哈哈哈哈哈</d><d p="9.54800,1,25,16777215,1588515778,0,e9f67161,32177443620519943">祖传开头呢？</d><d p="109.00000,1,25,16777215,1588473942,0,f3fac8ef,32155509925609477">！</d><d p="101.45500,1,25,16777215,1588473934,0,f3fac8ef,32155505606524931">！！！！！！！！！！！！！！！！！！</d><d p="88.93400,1,25,16777215,1588473922,0,f3fac8ef,32155499072323591">！！！！！！！！！！！！！！！</d><d p="82.28300,1,25,16777215,1588473915,0,f3fac8ef,32155495559069699">！！！！！！！！！！！！！！！</d><d p="76.02900,1,25,16777215,1588473909,0,f3fac8ef,32155492275454019">！！！！！！！！！！！！！！</d><d p="69.51900,1,25,16777215,1588473902,0,f3fac8ef,32155488859717635">！！！！！！！！！！！！！！</d><d p="59.38500,1,25,16777215,1588473892,0,f3fac8ef,32155483566506055">！！！！！！！！！！！！！！</d><d p="13.54600,1,25,16777215,1588473846,0,f3fac8ef,32155459510599683">祖传开头</d><d p="27.25600,1,25,16777215,1588432317,0,281ff078,32133686366306307">wc，你是两年半的练习生吗？</d><d p="7.67200,1,25,16777215,1588432146,0,281ff078,32133596538470403">在来亿遍</d><d p="3.29300,1,25,16777215,1588414598,0,8da34e6b,32124396580634631">来了来了</d><d p="17.50400,1,25,16777215,1588414507,0,8da34e6b,32124348486647815">来了来了</d><d p="23.86000,1,25,16777215,1588395056,0,ccd2efa3,32114150863273987">火钳刘明</d><d p="41.64300,1,25,16777215,1588390940,0,cdd27e85,32111992982994949">祖传开头</d><d p="45.27900,1,25,16777215,1588364169,0,9fd76d89,32097957258985477">哈哈哈哈哈哈哈哈哈哈哈哈哈哈哈哈哈哈哈</d><d p="102.59200,1,25,10546688,1588340721,0,c222cae5,32085663398494215">hhhhhhhhhhhhhhhhhhhhhhhhhhhhhhhhhhhhh</d><d p="79.54000,1,25,10546688,1588340686,0,c222cae5,32085645124435973">由 YELLOW 转 GREEN</d><d p="27.90500,1,25,16646914,1588340566,0,c222cae5,32085582255489027">2 years half practiser?</d><d p="72.16700,1,25,16777215,1588328700,0,b62133f2,32079360826015749">这是什么虎狼之词</d><d p="56.98200,1,25,16777215,1588326973,0,25781f41,32078455596646405">⎛⎝≥⏝⏝≤⎠⎞    ⎛⎝≥⏝⏝≤⎠⎞    ⎛⎝≥⏝⏝≤⎠⎞    ⎛⎝≥⏝⏝≤⎠⎞   ⎛⎝≥⏝⏝≤⎠⎞</d><d p="101.04500,1,25,16777215,1588307167,0,8194aa65,32068071788118021">⎛⎝≥⏝⏝≤⎠⎞    ⎛⎝≥⏝⏝≤⎠⎞    ⎛⎝≥⏝⏝≤⎠⎞    ⎛⎝≥⏝⏝≤⎠⎞    ⎛⎝≥⏝⏝≤⎠⎞   ⎛⎝≥⏝⏝≤⎠⎞⎛⎝≥⏝⏝≤⎠⎞    ⎛⎝≥⏝⏝≤⎠⎞</d><d p="89.57200,1,25,16777215,1588307156,0,8194aa65,32068065777156101">⎛⎝≥⏝⏝≤⎠⎞    ⎛⎝≥⏝⏝≤⎠⎞    ⎛⎝≥⏝⏝≤⎠⎞    ⎛⎝≥⏝⏝≤⎠⎞    ⎛⎝≥⏝⏝≤⎠⎞   ⎛⎝≥⏝⏝≤⎠⎞⎛⎝≥⏝⏝≤⎠⎞    ⎛⎝≥⏝⏝≤⎠⎞    ⎛⎝≥⏝⏝≤⎠⎞</d><d p="42.09900,1,25,16777215,1588246033,0,8bd7f953,32036019802472455">？？？</d><d p="73.75000,1,25,16777215,1588217045,0,c386bcff,32020821899214853">哈哈哈哈哈哈哈哈哈哈哈哈哈哈哈哈哈哈哈哈哈</d><d p="88.74100,1,25,16777215,1588212212,0,e887a881,32018287838625799">旋律不错</d><d p="56.77800,1,25,16777215,1588071623,0,19611c63,31944578594504707">哈哈哈哈</d><d p="50.57900,1,25,16777215,1588045601,0,dd6e9c86,31930935618830343">我来证明你开d</d><d p="61.35500,1,25,16777215,1587993514,0,1815c7e5,31903627163467779">紫妹小时候演技就很棒</d><d p="50.68800,1,25,16777215,1587993491,0,1815c7e5,31903614942838787">紫妹小时候就很可爱</d><d p="8.74000,1,25,16777215,1587973537,0,1275aeb2,31893153228783619">钉钉时代已经过去了，我们迎来了永动机时代</d><d p="107.80400,1,25,16777215,1587964095,0,6db4f13e,31888202995335171">噜噜噜</d><d p="59.80600,1,25,16777215,1587964047,0,6db4f13e,31888177765548039">快点打我</d><d p="24.25800,1,25,16777215,1587953657,0,41548e4c,31882730571563011">⎛⎝≥⏝⏝≤⎠⎞    ⎛⎝≥⏝⏝≤⎠⎞    ⎛⎝≥⏝⏝≤⎠⎞    ⎛⎝≥⏝⏝≤⎠⎞    ⎛⎝≥⏝⏝≤⎠⎞⎛⎝≥⏝⏝≤⎠⎞    ⎛⎝≥⏝⏝≤⎠⎞    ⎛⎝≥⏝⏝≤⎠⎞    ⎛⎝≥⏝⏝≤⎠⎞</d><d p="27.52200,1,25,38979,1587899674,0,93d79e71,31854428001140739">给他带顶帽</d><d p="21.62000,1,25,16777215,1587890037,0,73834ec5,31849375366905861">哈哈哈</d><d p="37.50200,1,25,52480,1587821547,0,f0826cd5,31813466863960069">虎狼之词</d><d p="34.88000,1,25,16777215,1587821533,0,f0826cd5,31813459364544519">虎狼之词</d><d p="81.36500,1,25,52480,1587813880,0,e6b9c411,31809447155728387">哦？</d><d p="8.21000,1,25,52480,1587783198,0,938dd429,31793361197203463">祖传开头</d><d p="6.86400,1,25,52480,1587783179,0,938dd429,31793351169146885">祖传开头绿</d><d p="7.26100,1,25,16777215,1587717554,0,d59fa36b,31758944519061511">再来亿次</d><d p="105.17200,1,25,16777215,1587705182,0,df62a911,31752457959768067">哈哈哈哈哈哈哈哈</d><d p="83.65600,1,25,16777215,1587645033,0,fc66d12c,31720922845544455">？？？</d><d p="32.23900,1,25,16777215,1587557775,0,a48a9e80,31675174400557063">哈哈哈哈嗝</d><d p="52.32900,1,25,16777215,1587549152,0,e9d72ed4,31670653519134723">⎛⎝≥⏝⏝≤⎠⎞    ⎛⎝≥⏝⏝≤⎠⎞    ⎛⎝≥⏝⏝≤⎠⎞    ⎛⎝≥⏝⏝≤⎠⎞   ⎛⎝≥⏝⏝≤⎠⎞</d><d p="63.75200,1,25,16777215,1587547048,0,d99bc32a,31669550155038723">⎛⎝≥⏝⏝≤⎠⎞    ⎛⎝≥⏝⏝≤⎠⎞    ⎛⎝≥⏝⏝≤⎠⎞    ⎛⎝≥⏝⏝≤⎠⎞    ⎛⎝≥⏝⏝≤⎠⎞   ⎛⎝≥⏝⏝≤⎠⎞</d><d p="23.15800,1,25,16777215,1587545323,0,8f55298d,31668646145687559">。。？？？？</d><d p="18.95800,1,25,16777215,1587545316,0,8f55298d,31668642227683335">。。。。</d><d p="21.81800,1,25,16777215,1587545081,0,9508dcd1,31668519127482375">哈哈哈哈</d><d p="29.74800,1,25,52480,1587533023,0,fde9e7a7,31662197208776707">________________________________________________</d><d p="20.50200,1,25,52480,1587533014,0,fde9e7a7,31662192286236679">_____________________________________________________________</d><d p="108.99200,1,25,16777215,1587486183,0,db327d63,31637639465533445">哈哈哈哈哈哈哈哈哈</d><d p="33.33200,1,25,16777215,1587483129,0,e0af6f5f,31636038194036741">优秀</d><d p="35.58500,1,25,16777215,1587482815,0,dc41c7bb,31635873517273093">DY以盗</d><d p="11.58800,1,25,16777215,1587482790,0,dc41c7bb,31635860491862023">DY</d><d p="46.44800,1,25,16777215,1587475886,0,8dbc68ba,31632241192861703">牛</d><d p="13.89900,1,25,16777215,1587475523,0,e1528c9e,31632050685476867">▅▆▇█▇▆▅▄▄▅▆▇█▇▆▄▄▅▆▇█▇▆▅▄▄▅▆▇█▇▆▅▄▄▅▆▇█▇▆▅▄▄▅▆▇█▇▆▅▄▄▅▆▇█▇▆▅▄▄▅▆▇█▇▆▅▄▄▅▆▇█▇▆▄▄▅▆█▇▆▅▄▅▆▇█▇▅▆▇█▇▆▅▄▄</d><d p="33.99600,1,25,9599289,1587466528,0,3e10c815,31627334608486407">哈哈哈哈哈哈哈哈哈哈哈哈哈哈哈哈哈哈哈哈哈</d><d p="16.12500,1,25,16777215,1587458482,0,b03d28b4,31623116220792839">⎛⎝≥⏝⏝≤⎠⎞    ⎛⎝≥⏝⏝≤⎠⎞    ⎛⎝≥⏝⏝≤⎠⎞    ⎛⎝≥⏝⏝≤⎠⎞    ⎛⎝≥⏝⏝≤⎠⎞⎛⎝≥⏝⏝≤⎠⎞    ⎛⎝≥⏝⏝≤⎠⎞    ⎛⎝≥⏝⏝≤⎠⎞    ⎛⎝≥⏝⏝≤⎠⎞</d><d p="48.04300,1,25,16765698,1587372651,0,cb6d952f,31578115910139907">hhhhhc</d><d p="35.83700,1,25,16777215,1587359382,0,b2ac1e56,31571159280517127">哈哈哈哈哈哈。</d><d p="63.50500,1,25,16776960,1587350991,0,3d535155,31566759735590919">？？？？？？？？？？？？？？？？？？？？？？？？？？？？？？？？？？？？？？？？？？？？？？？？？？？？？？？？？？？？？？？？？？？？？？？？？？？？？？？？？？？？？？？？？？</d><d p="106.42600,1,25,38979,1587310944,0,5d2d4bee,31545763823091719">？？？？？？？？？？？？？？？？</d><d p="105.73700,1,25,16707842,1587297626,0,36f273ac,31538781306224643">看英文字母</d><d p="50.90500,1,25,38979,1587290863,0,5bcbd340,31535235521314823">哈哈哈哈哈哈哈哈哈哈哈哈哈哈哈哈哈哈哈哈哈哈哈哈哈哈哈哈哈哈哈哈哈哈哈哈哈哈哈哈哈哈哈哈哈哈哈哈哈哈哈哈哈哈哈哈哈哈哈哈哈哈哈哈哈</d><d p="42.19400,1,25,38979,1587290832,0,5bcbd340,31535219153043463">哈哈哈哈哈哈哈哈哈哈哈哈哈哈哈哈哈哈哈哈哈哈哈哈哈哈哈哈哈哈哈哈哈哈哈哈哈哈哈哈哈哈哈哈哈哈哈哈哈哈哈哈哈哈哈哈哈哈哈哈哈哈哈哈哈哈哈哈哈哈哈哈哈哈哈哈哈哈哈哈哈哈哈哈哈哈哈哈哈哈哈哈哈哈哈哈哈哈</d><d p="6.25900,1,25,16777215,1587282737,0,31bb80af,31530975283904517">撒贝宁小朋盆友</d><d p="6.71800,1,25,16777215,1587175851,0,e887a881,31474936212094981">祖传开头</d><d p="107.44400,1,25,16777215,1587122691,0,57b0c562,31447065011159047">下次也不一定</d><d p="29.26300,1,25,16777215,1587100370,0,c3d3ee7,31435362575843331">？？？？？</d><d p="21.81400,1,25,16777215,1587092880,0,686aafec,31431435722686467">哈哈哈哈哈哈</d><d p="100.57400,1,25,16777215,1587088024,0,bfb3b181,31428889357582339">变色</d><d p="71.48000,1,25,16777215,1587035582,0,2b7ee03a,31401395086163971">喵内喵内</d><d p="9.27800,1,25,16777215,1587035497,0,d81a773d,31401350456672261">▄▅▆▇█▇▆▅▄▄▅▆▇█▇▆▅▄▄▅▆▇█▇▆▅▄▄▅▆▇█▇▆▅▄▄▅▆▇█▇▆▅▄▄▅▆█▇▆▅▄▄▅▆▇█▇▆▅▄▄▅▆▇█▇▆▅▄▄▅▆▇█▇▆▅▄▄▅▆▇█▇▆▅▄▄▅▆▇█▇▆</d><d p="79.78800,1,25,16777215,1587024542,0,431235a1,31395606619488259">注意看英文</d><d p="30.11300,1,25,16777215,1587024477,0,431235a1,31395572573798403">英文是原文注意看</d><d p="42.70800,1,25,16777215,1587015929,0,3a687ed6,31391090835718151">红红火火恍恍惚惚</d><d p="83.64000,1,25,16777215,1587008672,0,a886f506,31387286417440771">哈哈哈哈哈哈哈哈哈哈哈哈哈哈哈哈哈哈哈哈</d><d p="65.75200,1,25,16777215,1587006217,0,201fdfa6,31385999365898243">哈哈哈哈呵呵呵呵嘿嘿嘿哈哈哈哈呵呵呵呵嘿嘿嘿</d><d p="52.35700,1,25,16777215,1587006204,0,201fdfa6,31385992365604871">哈哈哈哈呵呵呵呵嘿嘿嘿哈哈哈哈呵呵呵呵嘿嘿嘿哈哈哈哈呵呵呵呵嘿嘿嘿哈哈哈哈呵呵呵呵嘿嘿嘿哈哈哈哈呵呵呵呵哈哈</d><d p="100.74100,1,25,16777215,1586997633,0,a886f506,31381498482393093">哈哈哈哈哈哈</d><d p="107.20000,1,25,16777215,1586941749,0,f69292d4,31352199188054023">开头见</d><d p="100.19700,1,25,16777215,1586939197,0,a886f506,31350861134823427">哈哈哈哈好</d><d p="79.18700,1,25,16777215,1586939176,0,a886f506,31350850116911111">哈哈哈哈</d><d p="93.79800,1,25,16777215,1586938774,0,a886f506,31350639646736387">哈哈哈哈哈</d><d p="51.98200,1,25,16777215,1586938732,0,a886f506,31350617734119427">哈哈哈哈哈哈哈哈哈</d><d p="12.60400,1,25,16777215,1586938565,0,a886f506,31350530070020099">hhhhhhhhhhh</d><d p="30.25400,1,25,16777215,1586938361,0,a886f506,31350423235854343">哈哈哈哈哈哈哈哈哈哈哈哈哈哈哈哈哈哈哈</d><d p="57.77400,1,25,16777215,1586928791,0,f8d3c7d9,31345405844258821">害怕</d><d p="10.52900,1,25,16646914,1586922182,0,430ab4f6,31341940413300739">奥利给！！！！！！！！！！！！！！！！！！！！！！！！！！！！！！！！！！！！！！！！！！！！！！！</d><d p="80.55800,1,25,16776960,1586909894,0,e48df09e,31335498150051847">WTG</d><d p="50.72800,1,25,16646914,1586909864,0,e48df09e,31335482185482245">哈哈哈哈哈</d><d p="44.03800,1,25,16777215,1586909857,0,e48df09e,31335478674849799">哈哈哈哈</d><d p="92.97800,1,25,16777215,1586872035,0,cf33641f,31315648941391875">曹操的英文翻译?f**k f**k?</d><d p="59.54800,1,25,16777215,1586842488,0,aeefb911,31300157744611333">哈哈哈哈哈哈哈哈</d><d p="31.15100,1,25,16777215,1586836897,0,b53570de,31297226588815365">哈哈哈哈哈哈哈哈哈哈哈哈哈哈哈哈哈</d><d p="59.96600,1,25,16707842,1586831101,0,46d2b047,31294187746885637">？？？</d><d p="11.90300,1,25,16777215,1586782089,0,c7285240,31268491283136517">祖传开头呢</d><d p="31.27300,1,25,16777215,1586780631,0,9508dcd1,31267727282274307">哈哈哈</d><d p="108.83000,1,25,16777215,1586776831,0,e4c76f81,31265734997311495">。。</d><d p="100.43000,1,25,16777215,1586760504,0,d64075e9,31257174875308037">。                                                                                                  。</d><d p="76.96900,1,25,16777215,1586760481,0,d64075e9,31257162565550087">。</d><d p="80.34300,1,25,16777215,1586681730,0,4d2d1ecc,31215874516451333">⎛⎝≥⏝⏝≤⎠⎞   ⎛⎝≥⏝⏝≤⎠⎞⎛⎝  ≥⏝⏝≤⎠⎞    ⎛⎝≥⏝⏝≤⎠⎞    ⎛⎝≥⏝⏝≤⎠⎞⎛⎝≥⏝⏝≤⎠⎞   ⎛⎝≥⏝⏝≤⎠⎞⎛⎝  ≥⏝⏝≤⎠⎞    ⎛⎝≥⏝⏝≤⎠⎞</d><d p="65.45500,1,25,16777215,1586681715,0,4d2d1ecc,31215866695647237">⎛⎝≥⏝⏝≤⎠⎞   ⎛⎝≥⏝⏝≤⎠⎞⎛⎝  ≥⏝⏝≤⎠⎞    ⎛⎝≥⏝⏝≤⎠⎞    ⎛⎝≥⏝⏝≤⎠⎞</d><d p="70.11300,1,25,16777215,1586618551,0,b7381a38,31182750681137157">？？？？</d><d p="17.05500,1,25,16777215,1586618498,0,b7381a38,31182722844065795">淦</d><d p="28.00200,1,25,16777215,1586531290,0,8d6ea738,31137000590409731">哈哈哈哈哈哈</d><d p="32.40400,1,25,6830715,1586516949,0,9985cd4c,31129481656664071">卧操</d><d p="40.17000,1,25,52480,1586513207,0,6d5174f8,31127519947653125">⎛⎝≥⏝⏝≤⎠⎞    ⎛⎝≥⏝⏝≤⎠⎞    ⎛⎝≥⏝⏝≤⎠⎞    ⎛⎝≥⏝⏝≤⎠⎞   ⎛⎝≥⏝⏝≤⎠</d><d p="20.49200,1,25,52480,1586494779,0,6b0f227f,31117858379923461">⎛⎝≥⏝⏝≤⎠⎞    ⎛⎝≥⏝⏝≤⎠⎞      ⎛⎝≥⏝⏝≤⎠⎞   ⎛⎝≥⏝⏝≤⎠⎞⎛⎝≥⏝⏝≤⎠⎞    ⎛⎝≥⏝⏝≤⎠⎞    ⎛⎝≥⏝⏝≤⎠⎞    ⎛⎝≥⏝⏝≤⎠⎞   ⎛⎝≥⏝⏝≤⎠⎞</d><d p="67.05100,1,25,16776960,1586488901,0,ae945e2f,31114776568922181">▂▃▄▅▆▅▄▃▂▂▃▄▅▆▅▄▃▂▂▃▄▅▆▅▄▃▂▂▃▂▂▃▄▅▆▆▅▄▃▂▂▃▄▂▃▄▅▆▅▄▂▃▄▅▆▅▄▃▂▂▃▄▅▆▅▄▃▂▂▃▄▅▆▅▄▃▂▂▃▂▂▃▄▅▆▆▅▄▃▂▂▃▄▂▃</d><d p="60.65600,1,25,16777215,1586488875,0,ae945e2f,31114762901782535">⎛⎝≥⏝⏝≤⎠⎞    ⎛⎝≥⏝⏝≤⎠⎞    ⎛⎝≥⏝⏝≤⎠⎞    ⎛⎝≥⏝⏝≤⎠⎞    ⎛⎝≥⏝⏝≤⎠⎞   ⎛⎝≥⏝⏝≤⎠⎞</d><d p="23.74200,1,25,16777215,1586439504,0,223be15f,31088878144192583">爱是一道光，绿到你发慌</d><d p="80.46600,1,25,16777215,1586433707,0,253384be,31085839212085255">⎛⎝≥⏝⏝≤⎠⎞    ⎛⎝≥⏝⏝≤⎠⎞    ⎛⎝≥⏝⏝≤⎠⎞    ⎛⎝≥⏝⏝≤⎠⎞    ⎛⎝≥⏝⏝≤⎠⎞</d><d p="43.34500,1,25,16777215,1586423930,0,56399465,31080712944222215">⎛⎝≥⏝⏝≤⎠⎞    ⎛⎝≥⏝⏝≤⎠⎞    ⎛⎝≥⏝⏝≤⎠⎞    ⎛⎝≥⏝⏝≤⎠⎞   ⎛⎝≥⏝⏝≤⎠</d><d p="97.00900,1,25,16777215,1586415905,0,2550884e,31076505607471109">有病吧</d><d p="29.18700,1,25,16707842,1586410204,0,a25bed94,31073516594397191">yellow?????????</d><d p="58.76900,1,25,16777215,1586398476,0,c2b8e415,31067367765704709">⎛⎝≥⏝⏝≤⎠⎞    ⎛⎝≥⏝⏝≤⎠⎞    ⎛⎝≥⏝⏝≤⎠⎞    ⎛⎝≥⏝⏝≤⎠⎞   ⎛⎝≥⏝⏝≤⎠⎞  ⎛⎝≥⏝⏝≤⎠⎞    ⎛⎝≥⏝⏝≤⎠⎞    ⎛⎝≥⏝⏝≤⎠⎞   ⎛⎝≥⏝⏝≤⎠⎞</d><d p="10.18700,1,25,16777215,1586364981,0,b0c29d02,31049806580809731">我想把这玩意染成绿</d><d p="3.97800,1,25,16777215,1586351971,0,9749dbab,31042985958834181">恭喜你发现宝藏歌曲（手动滑稽</d><d p="17.70000,1,25,16777215,1586348979,0,b3675852,31041417261350979">钉钉时代</d><d p="98.21300,1,25,16776960,1586334608,0,5564b17,31033882809729029">？？？？？？？？？？？？？？？？？？？？？？？？？？？？？？？？？？？？？？？？？？？？？？？？？？？？？？？？？？？？？？？？？？？？？？？？？？？？？？？？？？？？？？？？？？？？？？？？？？？？</d><d p="103.10900,1,25,16777215,1586324462,0,dfbc1676,31028562957434951">哈哈哈哈哈哈哈哈哈哈哈哈哈哈哈哈哈哈哈哈哈哈哈哈哈哈哈哈哈哈哈哈哈哈哈哈哈哈哈哈哈哈哈哈哈哈哈哈哈哈哈哈哈哈哈哈哈哈哈哈哈哈哈哈哈哈哈哈哈哈哈哈哈哈哈哈哈哈哈哈哈哈哈哈哈哈哈哈哈哈哈哈哈哈哈哈哈哈哈哈</d><d p="55.53000,1,25,16777215,1586321215,0,128f51c4,31026860715409411">⎛⎝≥⏝⏝≤⎠⎞    ⎛⎝≥⏝⏝≤⎠⎞    ⎛⎝≥⏝⏝≤⎠⎞    ⎛⎝≥⏝⏝≤⎠⎞   ⎛⎝≥⏝⏝≤⎠⎞  ⎛⎝≥⏝⏝≤⎠⎞    ⎛⎝≥⏝⏝≤⎠⎞    ⎛⎝≥⏝⏝≤⎠⎞   ⎛⎝≥⏝⏝≤⎠⎞</d><d p="6.02500,1,25,16777215,1586320079,0,530b4c3f,31026265193447429">▄▅▆▇█▇▆▅▄▄▅▆▇█▇▆▅▄▄▅▆▇█▇▆▅▄▄▅▆▇█▇▆▅▄▄▅▆▇█▇▆▅▄▄▅▆▇█▇▆▅▄▄▅▆▇█▇▆▅▄▄▅▆▇█▇▆▅▄▄▅▆▇█▇▆▅▄▄▅▆▇█▇▆▅▄▄▅▆▇█▇▆▅▄</d><d p="42.38900,1,25,16777215,1586318031,0,9394e5c5,31025191321075715">刘星：我想把这玩意染成绿的</d><d p="84.52800,1,25,16777215,1586309783,0,8a5c4c8d,31020867157229571">⎛⎝≥⏝⏝≤⎠⎞    ⎛⎝≥⏝⏝≤⎠⎞    ⎛⎝≥⏝⏝≤⎠⎞    ⎛⎝≥⏝⏝≤⎠⎞    ⎛⎝≥⏝⏝≤⎠⎞   ⎛⎝≥⏝⏝≤⎠⎞</d><d p="106.53200,1,25,16777215,1586305187,0,bcb260b1,31018457398509635">(((((ી(･◡･)ʃ)))))</d><d p="25.98100,1,25,16777215,1586271955,0,10b125ee,31001034233479173">哈哈哈哈哈哈哈哈哈哈啊哈哈哈哈哈哈哈哈哈哈哈哈哈哈哈哈哈哈哈哈哈哈哈哈哈哈啊哈哈哈哈哈哈哈哈啊哈哈哈哈啊哈哈哈哈哈哈哈啊哈哈啊哈哈啊哈哈哈啊哈啊哈哈哈哈哈哈哈啊哈哈啊哈哈啊哈哈哈啊哈哈哈哈啊哈哈哈哈哈</d><d p="73.14400,1,25,16777215,1586271888,0,10b125ee,31000999057424387">哈哈哈哈哈啊哈哈哈哈啊哈哈哈哈哈哈哈啊哈哈啊哈哈啊哈哈哈啊哈哈哈哈啊哈哈哈哈哈哈哈哈哈哈啊哈哈哈哈啊哈哈哈哈哈哈哈啊哈哈啊哈哈啊哈哈哈啊哈哈哈哈啊哈哈哈哈哈哈哈哈哈哈啊哈哈哈哈啊哈哈哈哈哈哈哈啊哈哈啊</d></i><?xml version="1.0" encoding="UTF-8"?><i><chatserver>chat.bilibili.com</chatserver><chatid>116417370</chatid><mission>0</mission><maxlimit>500</maxlimit><state>0</state><real_name>0</real_name><source>k-v</source><d p="4.34100,1,25,16777215,1606661025,0,715de77a,41690778951483397">1</d><d p="44.91800,1,25,16777215,1606557436,0,6107bd3,41636468520124419">杨紫</d><d p="106.90100,1,25,16777215,1606361678,0,b769a03c,41533834842865671">孙家坡</d><d p="95.10300,1,25,16777215,1606361672,0,b769a03c,41533831785218055">孙家坡好评</d><d p="84.18200,1,25,16777215,1606361666,0,b769a03c,41533828908974087">637好评</d><d p="55.01900,1,25,16777215,1606361652,0,b769a03c,41533821270097927">古城</d><d p="38.56000,1,25,16777215,1606361643,0,b769a03c,41533816941576199">至开往古城站</d><d p="86.26500,1,25,16777215,1606230288,0,4340e07f,41464948736393219">笑死我了哈哈</d><d p="29.61000,1,25,16707842,1606007196,0,7fb9dd70,41347984305160195">？？？？</d><d p="58.08600,1,25,16777215,1605962252,0,19d79521,41324420909760515">牛逼，哈哈优秀</d><d p="4.27900,1,25,16777215,1605764827,0,2ff7bc68,41220913495539719">演技巅峰</d><d p="13.16200,1,25,16777215,1605103492,0,35c4af88,40874183246741511">红豆劲敌</d><d p="26.66000,1,25,38979,1605003916,0,bfb45699,40821976567119879">??????</d><d p="14.29900,1,25,16777215,1604840819,0,d0e8aae9,40736466965364739">入伏</d><d p="5.42600,1,25,14811775,1604840795,0,d0e8aae9,40736454168018951">结婚的哥我都没任何附加r分</d><d p="56.71400,1,25,16777215,1604809531,0,24633196,40720063274680323">哈哈哈哈</d><d p="85.41200,1,25,16777215,1604804645,0,ef111ec2,40717501406380039">ou la ou la lololololol</d><d p="75.17200,1,25,16777215,1604726135,0,5394aa7,40676339619463171">红红火火恍恍惚惚</d><d p="105.73900,1,25,16777215,1604716885,0,e887a881,40671489681260549">哈哈哈</d><d p="102.37000,1,25,16777215,1604640768,0,7afb11a0,40631582346706951">？？？？？</d><d p="94.13000,1,25,16777215,1604640746,0,7afb11a0,40631571227607043">曹操的英文什么情况</d><d p="54.92000,1,25,16777215,1604146446,0,6bcd2c4f,40372415750995975">秀儿</d><d p="19.00000,1,25,16777215,1604146387,0,6bcd2c4f,40372384369213443">祖传开头</d><d p="84.99000,1,25,16777215,1604052159,0,ebb4ed5b,40322981937283079">？？？？？？？？？？？？？？</d><d p="36.14000,1,25,16777215,1603802404,0,2e3471d5,40192038541983749">NB </d><d p="77.67300,1,25,16777215,1603279713,0,4a97337,39917997787709447">哈哈哈哈哈哈哈哈哈哈</d><d p="12.36600,1,25,16777215,1602857568,0,30d6ab0a,39696672254066691">6</d><d p="106.55500,1,25,16777215,1602774865,0,ef18cca0,39653312248152071">哈哈哈哈哈哈哈哈</d><d p="88.21800,1,25,16777215,1602774847,0,ef18cca0,39653302630088711">俄语</d><d p="93.72100,1,25,16777215,1602759261,0,7c630b26,39645131004968967">害怕</d><d p="72.38200,1,25,16777215,1602599016,0,602f6863,39561116749135877">上瘾了</d><d p="19.98400,1,25,16777215,1602143472,0,a890774,39322280277835781">杨紫</d><d p="30.07900,1,25,16777215,1602135848,0,28c4343b,39318283194728451">▄▅▆▇█▇▆▅▄▄▅▆▇█▇▆▅▄▄▅▆▇█▇▆▅▄▄▅▆▇█▇▆▅▄▄▅▆▇█▇▆▅▄▄▅▆▇█▇▆▅▄▄▅▆▇█▇▆▅▄▄▅▆▇█▇▆▅▄▄▅▆▇█▇▆▄▄▅▄▄▄</d><d p="7.72400,1,25,16777215,1602135826,0,28c4343b,39318271500484611">▄▅▆▇█▇▆▅▄▄▅▆▇█▇▆▅▄▄▅▆▇█▇▆▅▄▄▅▆▇█▇▆▅▄▄▅▆▇█▇▆▅▄▄▅▆▇█▇▆▅▄▄▅▆▇█▇▆▅▄▄▅▆▇█▇▆▅▄▄▅▆▇█▇▆▄▄▅▆▇█▇▆▅▄▄▅▄▄▄</d><d p="43.48000,1,25,16777215,1602122974,0,8b4aa136,39311533387284487">绿的绿的</d><d p="73.62300,1,25,16777215,1602090070,0,54ba8afa,39294282057121795">哈哈哈哈</d><d p="83.48100,1,25,16777215,1602090021,0,54ba8afa,39294256692592647">哈哈哈</d><d p="78.62500,1,25,16777215,1601960279,0,6aad509d,39226234301317127">仙走一步</d><d p="11.82500,1,25,16777215,1601947051,0,347a567f,39219299180085253">祖传开头</d><d p="47.47400,1,25,16777215,1601944876,0,caded56b,39218158908735493">虎狼之词</d><d p="8.47200,1,25,16777215,1601922557,0,caded56b,39206457088933895">祖传开头</d><d p="73.81200,1,25,16777215,1601880045,0,190fbe53,39184168614100995">1.25倍数新世界</d><d p="54.71700,1,25,16777215,1601786645,0,c619c997,39135200239157251">哈哈哈哈哈哈哈哈哈哈哈哈哈哈哈哈哈哈哈哈哈哈哈哈哈哈哈哈哈哈哈哈哈哈哈哈哈哈哈哈哈哈哈哈哈哈哈哈哈哈哈哈哈哈哈哈哈哈哈哈哈哈哈哈哈</d><d p="42.69600,1,25,16777215,1601785397,0,896e0682,39134545763631111">哈哈哈哈哈哈</d><d p="14.78200,1,25,16777215,1601087903,0,52d6a897,38768857853722629">祖传开头</d><d p="10.47200,1,25,16777215,1601051425,0,92a93736,38749732916953091">考古</d><d p="38.28000,1,25,15138834,1600694447,0,3c9caf61,38562573890617347">妙啊</d><d p="100.86400,1,25,16777215,1600525946,0,d75ad3fc,38474230551019527">？？？？？？？？？？？？？？</d><d p="27.71200,1,25,16777215,1600525828,0,9792a508,38474169077727235">？？？？</d><d p="80.65200,1,18,16777215,1600498845,0,7d45de2d,38460022275440647">哈哈哈</d><d p="74.82000,1,25,38979,1600488072,0,7d0f9d84,38454374132875271">绿色（shar）的帽子（zhi）</d><d p="27.67000,1,25,16777215,1600451262,0,ca24b987,38435074805334021">哈哈</d><d p="8.91700,1,25,16777215,1600322597,0,ed5b7b7e,38367617169227781">祖传开头</d><d p="26.71500,1,25,16777215,1600314319,0,31a2eaf8,38363277259964485">牛</d><d p="18.87000,1,25,16707842,1600261162,0,4cb338dd,38335407535423493">觉觉：啊，轻点～</d><d p="93.06800,1,25,16777215,1600220336,0,94071fe6,38314003253428231">曹操：wdnmd</d><d p="10.92500,1,25,16777215,1600144735,0,54b1ee1e,38274366676926469">可以可以</d><d p="104.38000,1,25,16707842,1600079532,0,5835cf00,38240181176762375">▄▅▆▇█▇▆▅▄▄▅▆▇█▇▆▅▄▄▅▆▇█▇▆▅▄▄▅▆▇█▇▆▅▄▄▅▆▇█▇▆▅▄▄▅▆▇█▇▆▅▄▄▅▆▇█▇▆▅▄▄▅▆▇█▇▆▅▄▄▅▆</d><d p="100.08000,1,25,16777215,1600079521,0,5835cf00,38240175551676423">▄▅▆▇█▇▆▅▄▄▅▆▇█▇▆▅▄▄▅▆▇█▇▆▅▄▄▅▆▇█▇▆▅▄▄▅▆▇█▇▆▅▄▄▅▆▇█▇▆▅▄▄▅▆▇█▇▆▅▄▄▅▆▇█▇▆▅▄▄▅▆</d><d p="63.18000,1,25,16777215,1600079482,0,5835cf00,38240155040481285">哈哈哈哈哈哈哈哈哈哈哈哈哈哈哈哈哈哈哈哈哈哈哈哈哈哈哈哈哈哈哈哈哈哈哈哈哈哈哈哈哈哈哈哈哈哈哈哈哈哈哈哈哈哈哈哈哈哈哈哈哈哈哈哈哈哈哈哈哈哈哈哈哈哈哈哈哈哈哈哈哈哈哈哈哈哈哈哈哈哈哈哈哈哈哈哈哈哈呵呵</d><d p="41.73900,1,25,16777215,1600079438,0,5835cf00,38240132082958339">■■■■囍╋╋╋╋</d><d p="103.55800,1,25,2236962,1600070335,0,761995b9,38235359385485315">⎛⎝≥⏝⏝≤⎠⎞    ⎛⎝≥⏝⏝≤⎠⎞    ⎛⎝≥⏝⏝≤⎠⎞    ⎛⎝≥⏝⏝≤⎠⎞   ⎛⎝≥⏝⏝≤⎠⎞  ⎛⎝≥⏝⏝≤⎠⎞    ⎛⎝≥⏝⏝≤⎠⎞    ⎛⎝≥⏝⏝≤⎠⎞   ⎛⎝≥⏝⏝≤⎠⎞</d><d p="96.27800,1,25,16740868,1600070328,0,761995b9,38235355534589957">⎛⎝≥⏝⏝≤⎠⎞    ⎛⎝≥⏝⏝≤⎠⎞    ⎛⎝≥⏝⏝≤⎠⎞    ⎛⎝≥⏝⏝≤⎠⎞   ⎛⎝≥⏝⏝≤⎠⎞  ⎛⎝≥⏝⏝≤⎠⎞    ⎛⎝≥⏝⏝≤⎠⎞    ⎛⎝≥⏝⏝≤⎠⎞   ⎛⎝≥⏝⏝≤⎠⎞</d><d p="89.22100,1,25,10546688,1600070321,0,761995b9,38235351881875463">⎛⎝≥⏝⏝≤⎠⎞    ⎛⎝≥⏝⏝≤⎠⎞    ⎛⎝≥⏝⏝≤⎠⎞    ⎛⎝≥⏝⏝≤⎠⎞   ⎛⎝≥⏝⏝≤⎠⎞  ⎛⎝≥⏝⏝≤⎠⎞    ⎛⎝≥⏝⏝≤⎠⎞    ⎛⎝≥⏝⏝≤⎠⎞   ⎛⎝≥⏝⏝≤⎠⎞</d><d p="80.60000,1,25,13369971,1600070312,0,761995b9,38235347315326981">⎛⎝≥⏝⏝≤⎠⎞    ⎛⎝≥⏝⏝≤⎠⎞    ⎛⎝≥⏝⏝≤⎠⎞    ⎛⎝≥⏝⏝≤⎠⎞   ⎛⎝≥⏝⏝≤⎠⎞  ⎛⎝≥⏝⏝≤⎠⎞    ⎛⎝≥⏝⏝≤⎠⎞    ⎛⎝≥⏝⏝≤⎠⎞   ⎛⎝≥⏝⏝≤⎠⎞</d><d p="71.77800,1,25,16777215,1600070303,0,761995b9,38235342726234115">⎛⎝≥⏝⏝≤⎠⎞    ⎛⎝≥⏝⏝≤⎠⎞    ⎛⎝≥⏝⏝≤⎠⎞    ⎛⎝≥⏝⏝≤⎠⎞   ⎛⎝≥⏝⏝≤⎠⎞  ⎛⎝≥⏝⏝≤⎠⎞    ⎛⎝≥⏝⏝≤⎠⎞    ⎛⎝≥⏝⏝≤⎠⎞   ⎛⎝≥⏝⏝≤⎠⎞</d><d p="42.02700,1,25,16777215,1600048651,0,f83b87b0,38223990918479877">哈哈哈哈哈哈哈</d><d p="60.46500,1,25,16776960,1600002484,0,38b4787a,38199785882648581">？？？？？？？？</d><d p="25.46800,1,25,9487136,1599982083,0,f22aa5dd,38189089937686533">6</d><d p="32.26200,1,25,16777215,1599958731,0,bac20805,38176846961967111">优秀啊</d><d p="47.35600,1,25,16777215,1599934299,0,f7bf1e6e,38164037235113991">哈哈哈哈哈哈</d><d p="61.35800,1,25,16777215,1599813312,0,f83b87b0,38100605161963525">哈哈哈哈哈哈</d><d p="44.80200,1,25,16777215,1599212813,0,e340eb05,37785771017502725">哈哈哈哈哈</d><d p="109.00000,1,25,16777215,1599136239,0,4c1fb433,37745624291475459">你币有了</d><d p="15.02000,1,25,16777215,1598964162,0,e974daf7,37655406297219079">杨紫杨紫杨紫杨紫杨紫杨紫杨紫杨紫杨紫杨紫杨紫</d><d p="8.09300,1,25,16777215,1598958022,0,b3a24b90,37652186861142023">祖传开头</d><d p="108.99200,1,25,16777215,1598863765,0,eec1a159,37602769186586631">w</d><d p="83.43400,1,25,52480,1598579319,0,8111d4b6,37453637385977859">⎛⎝≥⏝⏝≤⎠⎞    ⎛⎝≥⏝⏝≤⎠⎞    ⎛⎝≥⏝⏝≤⎠⎞    ⎛⎝≥⏝⏝≤⎠⎞    ⎛⎝≥⏝⏝≤⎠⎞   ⎛⎝≥⏝⏝≤⎠⎞⎛⎝≥⏝⏝≤⎠⎞    ⎛⎝≥⏝⏝≤⎠⎞    ⎛⎝≥⏝⏝≤⎠⎞</d><d p="21.91500,1,25,52480,1598579257,0,8111d4b6,37453605150130183">▄▅▆▇█▇▆▅▄▄▅▆▇█▇▆▅▄▄▅▆▇█▇▆▅▄▄▅▆▇█▇▆▅▄▄▅▆▇█▇▆▅▄▄▅▆▇█▇▆▅▄▄▅▆▇█▇▆▅▄▄▅▆▇█▇▆▅▄▄▅▆▇█▇▆▅▄▄▅▆▇█▇▆▅▄▄▅▆▇█▇▆▅</d><d p="26.81400,1,25,16777215,1598540667,0,f53e298,37433373027729413">厉害厉害</d><d p="1.46100,1,25,16777215,1598439395,0,85bc72c,37380277165621253">▄▅▆▇█▇▆▅▄▄▅▆▇█▇▆▅▄▄▅▆▇█▇▆▅▄▄▅▆▇█▇▆▅▄▄▅▆▇█▇▆▅▄▄▅▆▇█▇▆▅▄▄▅▆▇█▇▆▅▄▄▅▆▇█▇▆▅▄▄▅▆▇█▇▆▅▄▄▅▆▇█▇▆▅▄▄▅▆▇█▇▆▅</d><d p="61.74200,1,25,16777215,1598416910,0,5ed57f59,37368488687828995">杨紫张一山黑历史</d><d p="15.19400,1,25,16777215,1598361701,0,e425e55d,37339543310434307">我的手机在震</d><d p="42.76400,1,25,16777215,1598317262,0,8de28f6a,37316244499595267">看一遍，笑一遍</d><d p="5.43800,1,25,16777215,1598274099,0,826fa486,37293614582202375">祖传开头</d><d p="99.62400,1,25,16777215,1598191103,0,92649a0a,37250100884930567">(づ ●─● )づ(づ ●─● )づ(づ ●─● )づ(づ ●─● )づ(づ ●─● )づ(づ ●─● )づ(づ ●─● )づ(づ ●─● )づ(づ ●─● )づ(づ ●─● )づ</d><d p="51.03900,1,25,16777215,1598064198,0,3839fb08,37183565690044421">哈哈哈哈哈哈哈哈哈哈哈哈哈哈哈哈哈哈哈哈哈哈哈哈哈哈哈哈哈哈哈哈哈哈哈哈哈哈哈哈哈哈哈哈哈哈哈哈哈哈哈哈哈哈哈哈哈哈哈哈哈哈哈哈</d><d p="51.76700,1,25,16777215,1597998906,0,646e93fc,37149333946630147">哈哈哈哈哈哈哈哈哈哈或或或或</d><d p="30.24800,1,25,41194,1597905905,0,b46210d9,37100574850678789">我都忘了原声了</d><d p="79.62700,1,25,16646914,1597754585,0,6feeff5c,37021239242915845">woc</d><d p="61.60800,1,25,16646914,1597754566,0,6feeff5c,37021229821460487">哈哈哈哈哈哈哈哈哈哈哈哈哈哈哈哈哈哈哈哈哈哈哈哈哈哈哈哈哈哈哈哈哈哈哈哈哈哈哈哈哈哈哈哈哈哈哈哈哈哈哈哈哈哈哈哈哈哈</d><d p="26.81400,1,25,16777215,1597754532,0,6feeff5c,37021211611365379">火钳刘明</d><d p="10.48600,1,25,16777215,1597754493,0,7792082f,37021191393247237">1</d><d p="7.74400,1,25,16777215,1597691472,0,3769972a,36988149900509187">？？？？？？？？？？？？？？？？？？？？？？？？？？？？？？？？？？？？？？？？？？？？？？？？？？？？？？？？？？？？？？？？？？？？？？？？？？？？？？？</d><d p="12.59900,1,25,16777215,1597548750,0,f594dab7,36913322803593223">哈哈</d><d p="4.96000,1,25,16777215,1597505680,0,b70f86d6,36890741453094919">祖传开头</d><d p="31.32400,1,25,16776960,1597502944,0,33974ef1,36889307036254213">yellow？</d><d p="103.26500,1,25,16777215,1597492611,0,a2f82281,36883889394810885">哈哈哈哈哈哈哈哈</d><d p="96.90400,1,25,16777215,1597492604,0,a2f82281,36883886101233671">老太太钻被窝</d><d p="80.23100,1,25,16777215,1597492588,0,a2f82281,36883877317836805">？？？？</d><d p="74.95000,1,25,16777215,1597492582,0,a2f82281,36883874587869191">哈哈哈哈哈哈</d><d p="64.66700,1,25,16777215,1597492572,0,a2f82281,36883869195042819">哈哈哈哈</d><d p="55.06100,1,25,16777215,1597492562,0,a2f82281,36883864167120903">哈哈哈哈华华姐</d><d p="47.34800,1,25,16777215,1597492555,0,a2f82281,36883860104413187">是</d><d p="40.55700,1,25,16777215,1597492548,0,a2f82281,36883856539779075">？？？？？</d><d p="30.83600,1,25,16777215,1597492538,0,a2f82281,36883851438456835">？？？？？</d><d p="19.74300,1,25,16777215,1597492527,0,a2f82281,36883845633015811">哈哈哈哈</d><d p="85.41800,1,25,16777215,1597470290,0,781362a5,36872187203289091">牛逼</d><d p="108.99200,1,25,52480,1597459929,0,e7cf8fcb,36866755127148551">哈哈哈哈哈哈哈哈哈哈哈哈哈哈哈哈哈哈哈哈哈哈哈哈哈哈哈哈哈哈哈哈哈哈哈哈哈哈哈哈哈哈哈哈哈哈哈哈哈哈哈哈哈哈哈哈哈哈哈哈哈哈哈哈</d><d p="95.85800,1,25,52480,1597459916,0,e7cf8fcb,36866748052930563">。。。。。。。。。。。。。。。。。。。。。。。。。。。。。。。。。。。。。。。。。。。。。。。。。。。。。。。。。。。。。。。。。。。。。。。。。。。。。。。。。。。。。。。。。。。。。。。。。。。。</d><d p="66.18200,1,25,52480,1597459886,0,e7cf8fcb,36866732477382659">？？？？？？？？？？？？？？？？？？？？？？？？？？？？？？？？？？？？？？？？？？？？？？？？？？？？？？？？？？？？？？？？？？？？？？？？？？？？？？？？？？？？？？？？？？？？？？？？？？？？</d><d p="70.19400,1,25,16777215,1597459834,0,e7cf8fcb,36866704983719939">哈哈哈哈哈哈哈哈哈哈哈哈哈哈哈哈哈哈哈哈哈哈哈哈哈哈哈哈哈哈哈哈哈哈哈哈哈哈哈哈哈哈哈哈哈哈哈哈哈哈哈哈哈哈哈哈哈哈哈哈哈哈哈哈哈哈哈哈哈哈哈哈哈哈哈哈哈哈哈哈哈哈哈哈哈哈哈哈哈哈哈哈哈哈哈哈哈哈哈哈</d><d p="61.40500,1,25,16777215,1597441223,0,6195a56a,36856947581911043">山哥紫妹太好玩了</d><d p="45.69600,1,25,16777215,1597386137,0,a41dcc9d,36828066497429511">绿的</d><d p="108.07800,1,25,16777215,1597253269,0,9d15167a,36758405483331589">染成绿哈哈哈哈笑死了</d><d p="68.83900,1,25,16777215,1597253184,0,9d15167a,36758361150062599">恐怖奶奶可还行</d><d p="7.32800,1,25,16777215,1597221927,0,a43a51de,36741973022343173">▁▃▅▇█▇▅▃▁▁▃▅▇█▇▅▃▁▁▃▅▇█▇▅▃▁▁▃▅▇█▇▅▃▁▁▃▅▇█▇▅▃▁▁▃▅▇█▇▅▃▁▁▃▅▇█▇▅▃▁▁▃▅▇█▇▅▃▁▁▃▅▇█▇▅▃▁▁▃▅▇█▇▅▃</d><d p="25.93200,1,25,16777215,1597208311,0,ce93e1cf,36734834503581699">凌潇肃</d><d p="70.99500,1,25,16777215,1597130182,0,8a4ede4a,36693872534880261">刘星是gay</d><d p="67.02700,1,25,16646914,1597048042,0,526ef1d1,36650807251697669">ohhhhhhhhhhhhhhhhhhhhhhhhhhhhhhhhhhhhhhhhhhhhhhhhhhhhhhhhhhhhhhh</d><d p="34.50100,1,25,52480,1597048009,0,526ef1d1,36650790213910535">哈哈哈哈哈哈哈哈哈哈哈哈哈哈哈哈哈哈哈哈哈哈哈哈哈哈哈哈哈哈哈哈哈哈哈哈哈哈哈哈哈哈哈哈哈哈哈哈哈哈哈哈哈哈哈哈哈哈哈哈哈哈哈哈</d><d p="78.70900,1,25,16777215,1597028896,0,2fe2f666,36640769324351495">已笑死</d><d p="31.61500,1,25,16777215,1597020312,0,e7cf8fcb,36636269184286727">秀儿</d><d p="8.27000,1,25,16776960,1596970160,0,dd647293,36609974750150663">呵呵呵呵呵呵呵呵呵呵呵呵呵呵呵呵呵呵呵呵呵呵呵呵呵呵呵呵呵呵呵呵呵呵呵呵呵呵呵呵呵呵呵呵呵呵呵呵呵呵呵呵呵呵呵呵呵呵呵呵呵呵呵呵呵呵呵呵呵呵呵呵呵呵呵呵呵呵呵呵呵呵呵呵呵呵呵呵呵呵呵呵呵呵呵呵呵呵呵呵</d><d p="77.54000,1,25,16776960,1596970123,0,dd647293,36609955442196483">呵呵呵呵呵呵呵呵呵呵呵呵呵呵呵呵呵呵呵呵呵呵呵呵呵呵呵呵呵呵呵呵呵呵呵呵呵呵呵呵呵呵呵呵呵呵呵呵呵呵呵呵呵呵呵呵呵呵呵呵呵呵呵呵</d><d p="70.06300,1,25,52480,1596952097,0,a9135c83,36600504446353411">哈哈哈哈哈哈哈哈哈哈哈哈哈哈哈哈哈哈哈哈哈哈哈哈哈哈哈哈哈哈哈哈哈哈哈哈哈哈哈哈哈</d><d p="62.56200,1,25,16777215,1596945245,0,f8fda4d0,36596912211099655">红红火火恍恍惚惚</d><d p="94.60900,1,25,16777215,1596935351,0,e1dd5b6c,36591725172490245">梅开二度</d><d p="61.79700,1,25,16777215,1596907527,0,b97a99d1,36577137189715971">哈哈哈</d><d p="56.44000,1,25,16777215,1596907522,0,b97a99d1,36577134359609347">太带感了</d><d p="64.39300,1,25,16777215,1596888433,0,3840b0fa,36567126465052677">恐怖奶奶</d><d p="11.54500,1,25,16777215,1596872208,0,11d70995,36558619708227589">来啦</d><d p="33.09700,1,25,16646914,1596866700,0,6917c84d,36555731931496453">⎛⎝≥⏝⏝≤⎠⎞    ⎛⎝≥⏝⏝≤⎠⎞    ⎛⎝≥⏝⏝≤⎠⎞    ⎛⎝≥⏝⏝≤⎠⎞    ⎛⎝≥⏝⏝≤⎠⎞   ⎛⎝≥⏝⏝≤⎠⎞⎛⎝≥⏝⏝≤⎠⎞    ⎛⎝≥⏝⏝≤⎠⎞    ⎛⎝≥⏝⏝≤⎠⎞</d><d p="15.23200,1,25,16777215,1596866680,0,6917c84d,36555721533816839">⎛⎝≥⏝⏝≤⎠⎞    ⎛⎝≥⏝⏝≤⎠⎞    ⎛⎝≥⏝⏝≤⎠⎞    ⎛⎝≥⏝⏝≤⎠⎞    ⎛⎝≥⏝⏝≤⎠⎞   ⎛⎝≥⏝⏝≤⎠⎞⎛⎝≥⏝⏝≤⎠⎞    ⎛⎝≥⏝⏝≤⎠⎞    ⎛⎝≥⏝⏝≤⎠⎞</d><d p="56.70900,1,18,15138834,1596825026,0,58b2d1ea,36533882842513411">哈哈哈哈哈哈哈哈哈</d><d p="104.50300,1,25,16777215,1596746883,0,6195a56a,36492913598791685">哈哈哈哈哈哈哈</d><d p="58.00100,1,25,16777215,1596746837,0,6195a56a,36492889260818439">哈哈哈哈哈哈哈</d><d p="78.02000,1,25,16777215,1596645387,0,b34c78d,36439700088029187">我选择死亡</d><d p="23.94300,1,25,16777215,1596625705,0,f53e298,36429381316378629">厉害厉害</d><d p="35.36600,1,25,52480,1596553484,0,33390eda,36391516744187907">原谅色</d><d p="34.70000,1,25,16777215,1596533780,0,9317e740,36381186011955205">妙啊</d><d p="93.09200,1,25,16777215,1596517763,0,f0b70a1b,36372788523565059">哈哈哈哈哈哈哈</d><d p="86.44000,1,25,16777215,1596517756,0,f0b70a1b,36372785036525571">哈哈哈哈哈哈哈</d><d p="81.95700,1,25,16777215,1596517752,0,f0b70a1b,36372782662025221">哈哈哈哈哈哈哈</d><d p="78.09900,1,25,16777215,1596517748,0,f0b70a1b,36372780653477891">哈哈哈哈哈哈哈</d><d p="73.06400,1,25,16777215,1596517743,0,f0b70a1b,36372778005823493">哈哈哈哈哈哈哈</d><d p="9.79200,1,25,16777215,1596510229,0,edd6c04e,36368838458605573">祖传开头</d><d p="75.52000,1,25,16777215,1596463569,0,ede0610c,36344375526555651">？？？？？？？</d><d p="60.79900,1,25,16777215,1596448963,0,d1b3b49a,36336717416366087">老太太钻被窝哈哈哈哈哈哈哈哈哈哈哈</d><d p="52.27900,1,25,16777215,1596448942,0,d1b3b49a,36336706463989767">百万配音</d><d p="43.85200,1,25,16707842,1596442446,0,53eb4fa8,36333300555448327">你币有了★</d><d p="58.81900,1,25,16777215,1596437160,0,2ae7a794,36330529596375045">哈哈哈哈哈</d><d p="52.02000,1,25,16777215,1596433682,0,8a6f785f,36328705647181829">绿色</d><d p="9.58900,1,25,16777215,1596389451,0,d6c6dda9,36305516022464515">请保护好自己</d><d p="76.39000,1,25,16777215,1596288734,0,7e0e6873,36252711612055557">n</d><d p="58.86100,1,25,16777215,1596274022,0,74404ec4,36244997957746693">牛皮！</d><d p="91.60900,1,25,16777215,1596259987,0,ff31436,36237639731904519">哈哈哈哈哈哈哈哈哈</d><d p="59.66400,1,25,16777215,1596259955,0,ff31436,36237622974611463">哈哈哈哈哈哈</d><d p="91.20800,1,25,16777215,1596171365,0,84275c8d,36191175986118659">勤快点打我</d><d p="4.24800,1,25,16777215,1596171265,0,84275c8d,36191123738722309">祖传开头</d><d p="103.82600,1,25,16777215,1596124644,0,fc422319,36166680795152389">文化文化</d><d p="27.74200,1,25,16777215,1596119221,0,520234d0,36163837545152519">哈哈哈哈h</d><d p="20.09700,1,25,16777215,1596010862,0,d3ea81ca,36107026590334979">hhhhhhhhhhhhhhhhh</d><d p="37.60900,1,25,16777215,1595954325,0,1e64c2d2,36077384640757765">自己的颜色</d><d p="28.10000,1,25,16777215,1595953969,0,a92b3ba5,36077198195032071">wdnmd好听</d><d p="48.24900,1,25,16777215,1595914335,0,1a7bc8a9,36056418229420101">这个夏雪真的很美</d><d p="45.81000,1,25,16777215,1595914256,0,1a7bc8a9,36056377257361415">这个夏雪真的很美哎</d><d p="58.01900,1,25,16777215,1595908708,0,f90407a,36053468374892551">红红火火恍恍惚惚哈哈哈哈哈哈</d><d p="71.66400,1,25,16777215,1595894432,0,1cbfb2a3,36045983807176711">O(∩_∩)O哈哈~</d><d p="93.40600,1,25,16777215,1595817097,0,24c54fc4,36005437555867655">f*ck是什么鬼</d><d p="11.77100,1,25,16777215,1595816753,0,10ffe7f9,36005257317711879">祖传开头</d><d p="84.61800,1,25,16777215,1595424027,0,78c06673,35799355972124679">不知道张一山看了会怎么样，嘻嘻嘻</d><d p="61.76100,1,25,16777215,1595423965,0,78c06673,35799323126530055">老太太钻被喔</d><d p="31.68200,1,25,16777215,1595423895,0,78c06673,35799286808576003">她的青春是绿色的</d><d p="104.06500,1,25,16777215,1595423558,0,3c7dbc38,35799109762285571">英语好评</d><d p="54.91600,1,25,16777215,1595422713,0,7cd173ff,35798667009982467">哈哈哈哈哈哈</d><d p="5.34000,1,25,16777215,1595418361,0,7e0641f,35796385302315011">祖传开头</d><d p="65.08200,1,25,16777215,1595387594,0,7a50ab56,35780254730027011">哈哈哈哈哈哈哈哈哈哈哈哈哈哈哈哈哈哈哈</d><d p="108.38500,1,25,16707842,1595387532,0,dc1b9585,35780221804216323">？？？？？？</d><d p="91.94800,1,25,16707842,1595387508,0,dc1b9585,35780209361289285">英文字幕？？？</d><d p="67.70000,1,25,16777215,1595350084,0,d726dc81,35760588301271043">仙走一步</d><d p="58.94400,1,25,16776960,1595338207,0,42546cc4,35754361303334915">老太太钻被窝</d><d p="46.41000,1,25,52480,1595338155,0,42546cc4,35754334293065733">?????</d><d p="62.14000,1,25,9487136,1595337317,0,98ce2a53,35753895079182339">老太太钻被窝，我变色了。</d><d p="35.99100,1,25,38979,1595337283,0,98ce2a53,35753876909981703">？？</d><d p="4.45700,1,25,16777215,1595337250,0,98ce2a53,35753859801415683">祖传开头。</d><d p="57.85400,1,25,16777215,1595238531,0,24ec912c,35702102536749059">哈哈哈哈哈哈哈好好</d><d p="31.31200,1,25,16777215,1595238504,0,24ec912c,35702088611135493">哈哈哈哈哈</d><d p="19.93400,1,25,16777215,1595171601,0,4e88ee36,35667011966074887">有才啊</d><d p="84.69900,1,25,16777215,1595165627,0,3b27a4b8,35663879937196037">𝗙𝗕𝗜! 𝗢𝗽𝗲𝗻 𝗧𝗵𝗲 𝗗𝗼𝗼𝗿!</d><d p="11.38300,1,25,16777215,1595156781,0,440fae72,35659241836511239">祖传开头</d><d p="107.84000,1,25,16777215,1595090588,0,8b7d66d2,35624537587449859">你说的好有道理，我竟然无力反驳。</d><d p="5.59000,1,25,16777215,1595079789,0,8eb4078c,35618876018393093">一天一遍，欢乐无限</d><d p="2.84100,1,25,16777215,1595035388,0,fde7c3a,35595596912394247">.</d><d p="96.86900,1,25,16777215,1594974057,0,2bab9ae0,35563441886855175">Kagura Mea,up老财布了</d><d p="33.71000,1,25,16777215,1594902293,0,a73c4432,35525816916377605">魔性</d><d p="17.79800,1,25,16777215,1594902254,0,a73c4432,35525796508991495">？？？？？？？？？？？？？？？？？？？？？？？？？？？？？？？？？？？？？？？？？？？？？？？？？？？？？？？？？？？？？？？</d><d p="103.93100,1,25,16777215,1594820952,0,ab21c144,35483170671427591">你币没了</d><d p="66.30500,1,25,16777215,1594714238,0,8bbcaa34,35427222144679943">2020 7 14</d><d p="41.47300,1,25,16777215,1594714213,0,8bbcaa34,35427209108258823">2020     7  13</d><d p="14.02200,1,25,16777215,1594714186,0,8bbcaa34,35427194730184707">2020</d><d p="89.74800,1,25,16777215,1594695752,0,18032f04,35417530241646599">秘籍:老太太钻被窝[滑稽]</d><d p="24.77400,1,25,16777215,1594622062,0,16cefd97,35378895196782599">hhh</d><d p="28.42600,1,25,16777215,1594526458,0,13691ea8,35328771137470469">哇⊙∀⊙！这播放量</d><d p="105.99400,1,25,16777215,1594490957,0,b37a1cac,35310158576353285">？？？？？？？？？？？？？？？？？？？？？？？？？？？？？？？？？？？？？？？？？？？？？？？？？？？？？？？？？？？？？？？？？？？？？？？？？？？？？？？？？？？？？？？？？？？？？？？？？？？？</d><d p="50.99800,1,25,16777215,1594484297,0,3b9795fd,35306666522574851">哈哈哈哈哈哈哈哈哈哈哈哈哈哈哈哈哈哈哈哈哈哈</d><d p="35.18900,1,25,16707842,1594293837,0,c7ae8ab6,35206811085176837">？？？</d><d p="22.96300,1,25,16707842,1594293825,0,c7ae8ab6,35206804661075973">？？？？</d><d p="5.99200,1,25,16777215,1594269749,0,4daa5daa,35194181538807811">笑死人不偿命</d><d p="109.00000,1,25,16777215,1594269733,0,4daa5daa,35194173642506247">笑死人不偿命</d><d p="81.88100,1,25,16777215,1594130399,0,27ac536c,35121122218344451">达瓦里氏！伏特加！！！！</d><d p="92.55900,1,25,16777215,1594103140,0,adbf856d,35106830871429127">黄色青春</d><d p="48.00500,1,25,16777215,1594103096,0,adbf856d,35106807504437251">搞颜色</d><d p="21.85700,1,25,16777215,1594103050,0,adbf856d,35106783289671687">生物课上搞颜色</d><d p="8.59000,1,25,16777215,1594103017,0,adbf856d,35106766338916357">欧耶</d><d p="91.39500,1,25,16777215,1594025866,0,eae06c0,35066316761071685">。0  。</d><d p="42.11800,1,25,16777215,1594025817,0,eae06c0,35066290967674887">6 6 6</d><d p="64.78800,1,25,16777215,1593951396,0,b51e5890,35027273300049925">哈哈哈哈哈哈哈哈哈哈哈哈</d><d p="78.05500,1,25,16776960,1593946685,0,60084373,35024803002318853">y***** again</d><d p="29.11500,1,25,16776960,1593946610,0,60084373,35024763772469251">嗯，我也有</d><d p="55.45900,1,25,16777215,1593944521,0,46f6a0ea,35023668830011399">笑死我了</d><d p="24.63500,1,25,16777215,1593915278,0,54a00b51,35008336693821445">祖传开头</d><d p="71.89100,1,25,16777215,1593879854,0,54fc637b,34989764427382787">淦淦淦淦淦淦淦淦淦淦淦淦淦淦淦淦淦淦淦淦</d><d p="20.24600,1,25,16776960,1593877948,0,ea1eb186,34988765349412867">？？？？</d><d p="61.14900,1,25,16777215,1593864178,0,2cc6eded,34981545808232451">我使用双节棍去打奶奶？？？？？？？</d><d p="80.37800,1,25,16777215,1593841784,0,6b399dfe,34969805052182533">哈哈哈哈哈弹幕一遍，英文一遍，中文一遍，哈哈哈哈哈哈哈哈哈</d><d p="78.76900,1,25,16777215,1593841644,0,6b399dfe,34969731593142279">哈哈哈哈哈哈</d><d p="7.27000,1,25,16777215,1593841573,0,6b399dfe,34969694254923783">哈哈哈哈哈哈哈哈哈哈哈</d><d p="96.83800,1,25,16777215,1593841415,0,6b399dfe,34969611179393029">哈哈哈哈哈哈哈哈哈哈哈哈哈</d><d p="58.83900,1,25,16777215,1593841376,0,6b399dfe,34969591119609863">哈哈哈哈哈哈哈哈哈哈哈哈哈哈哈</d><d p="26.83800,1,25,16777215,1593841344,0,6b399dfe,34969574393249797">哈哈哈哈哈哈哈哈哈哈哈哈</d><d p="45.10000,1,25,16777215,1593761158,0,1577b562,34927533855080453">哈哈哈</d><d p="18.64000,1,25,16777215,1593680066,0,1566c00c,34885018303070211">祖传开头呢</d><d p="10.66600,1,25,16777215,1593669599,0,3b3002b7,34879530247127045">祖传开头</d><d p="29.11600,1,25,15772458,1593611855,0,781678b2,34849255850508293">注意英文</d><d p="26.30200,1,25,16777215,1593413099,0,ebc6ff3e,34745050470547459">？？？</d><d p="42.44000,1,25,16777215,1593364521,0,e1056f7,34719581375299591">再来亿遍</d><d p="34.03800,1,25,38979,1593330463,0,f6afaf20,34701725400563719">绿</d><d p="13.22000,1,25,38979,1593168584,0,7dbf8006,34616854378446851">祖传</d><d p="32.11700,1,25,16777215,1593142859,0,7985427a,34603367045529605">哈哈哈哈哈哈哈哈哈哈笑死了</d><d p="12.91700,1,25,16777215,1592911896,0,1af4d980,34482275874242565">再来一遍</d><d p="37.18200,1,25,16777215,1592883771,0,78d5fad8,34467530024681477">卧槽牛逼</d><d p="93.60400,1,25,16777215,1592766356,0,ded297ae,34405970795823111">你币有了哈哈哈</d><d p="47.60400,1,25,16777215,1592766310,0,ded297ae,34405946626670599">哈哈哈哈哈</d><d p="62.21800,1,25,16777215,1592666440,0,68b3170,34353586056462343">哈哈哈</d><d p="63.24000,1,25,16777215,1592657477,0,76ec2ac5,34348886782902275">杀马特</d><d p="54.29200,1,18,9487136,1592632853,0,ce94c81a,34335977053356035"> 绿 色 </d><d p="27.67400,1,25,16646914,1592138375,0,a2d01483,34076728126078981">要素过多</d><d p="5.71500,1,25,41194,1592135041,0,5d999d5f,34074979854188547">新冠考古</d><d p="1.00300,1,25,16777215,1592111845,0,726b2c44,34062818672115717">600万贺电</d><d p="108.49600,1,25,16777215,1592036579,0,d55cc229,34023357753589765">把男同学打掉</d><d p="86.53400,1,25,16777215,1592036557,0,d55cc229,34023346243371015">哈哈哈哈哈哈哈哈哈哈哈哈哈哈哈哈哈哈哈</d><d p="85.80700,1,25,16777215,1591940667,0,1605aabd,33973071801483269">p p p p p p p p p p p p p p p p p p</d><d p="75.56000,1,25,16776960,1591802467,0,f14957a5,33900615579467783">？？？？？？？？？？？？？？？？？？？？？？？？？？？？？？？？？？？？？？？？？？？？</d><d p="20.11500,1,25,16776960,1591802412,0,f14957a5,33900586503503875">？？？？？？？？？？？？</d><d p="8.44100,1,25,16777215,1591802267,0,f29a2afa,33900510322360323">祖传开头</d><d p="105.14000,1,25,16777215,1591797746,0,bc3f02eb,33898140515958789">这旋律可以啊！</d><d p="41.90000,1,25,16777215,1591693308,0,5ba9b67c,33843384887541765">其实你开了弹幕</d><d p="74.74900,1,25,16777215,1591619923,0,17e0e765,33804910000603141">开始吟唱</d><d p="42.61300,1,25,16777215,1591604198,0,ff2c5066,33796665415041029">你币有了</d><d p="48.50500,1,25,52480,1591499530,0,d4d5ddb5,33741789217161223">？？？？？？？？？？？？？？？？？？？？、</d><d p="6.88900,1,25,16777215,1591498998,0,54a4d399,33741510319538183">哈哈哈哈</d><d p="70.43900,1,25,16777215,1591456273,0,72f8e94,33719110258917443">鹅鹅鹅</d><d p="70.70900,1,25,4351678,1591452659,0,c244b4b7,33717215558631429">淦</d><d p="93.92000,1,25,16777215,1591424925,0,50019da4,33702674601869315">hhhhh</d><d p="88.67400,1,25,16777215,1591423770,0,e927c517,33702069243215875">hhh</d><d p="70.06300,1,25,41194,1591380768,0,9ceb9ecf,33679523602497543">哈哈哈哈哈哈哈哈哈哈哈哈</d><d p="7.65500,1,25,16777215,1591364568,0,2e6009de,33671030155771911">来了</d><d p="108.11600,1,25,16777215,1591361951,0,c87ada0a,33669657994985475">？？？？？？？？？？？？？？</d><d p="62.54300,1,25,16777215,1591361905,0,c87ada0a,33669634125201411">？？？？？？？？？？？？</d><d p="96.74200,1,25,38979,1591302005,0,e887a881,33638229388820487">哈哈哈</d><d p="64.81000,1,25,16777215,1591301973,0,e887a881,33638212695490567">逐渐忘了原唱</d><d p="109.00000,1,25,16777215,1591279303,0,917c78f8,33626326918758407">哈哈哈哈哈</d><d p="5.26000,1,25,16777215,1591239926,0,2e1c7e4c,33605681745494021">绿了开头</d><d p="24.56300,1,25,16777215,1591081847,0,4a8ec77a,33522803212812293">笑死人</d><d p="23.16900,1,25,16777215,1591002778,0,890c3f2f,33481347842965509">哈哈哈哈哈哈哈哈</d><d p="79.14200,1,25,16777215,1590986920,0,52fde86c,33473033675472901">哈哈哈</d><d p="22.17100,1,25,16777215,1590934601,0,be0af480,33445603609935879">淦</d><d p="43.31700,1,25,38979,1590908926,0,1e39b43f,33432142382366725">绿</d><d p="0.00000,1,25,52480,1590843984,0,d5cebfcb,33398094033321991">祖传开头</d><d p="99.89600,1,25,16777215,1590834436,0,5522ee4c,33393088428769287">哈哈哈哈哈哈哈哈哈哈哈哈哈哈哈哈哈哈哈哈</d><d p="40.00600,1,25,16777215,1590834376,0,5522ee4c,33393057094696963">哈哈哈哈哈哈哈哈哈哈哈</d><d p="8.87800,1,25,16777215,1590822760,0,ea6e2423,33386966627123205">▂▃▅▆▇▇▆▅▃▂▂▃▅▆▇▇▆▅▃▂▃▅▆▇▇▆▅▃▂▂▃▅▆▇▇▆▅▃▂▃▅▆▇▇▆▅▃▂▂▃▅▆▇▇▆▅▃▂▃▅▆▇▇▆▅▃▂▂▃▅▆▇▇▆▅▃▂▂▃▅▆▇▇▆▅▃▂▃▅▆▇▇▆▅▃▂</d><d p="29.02200,1,25,16777215,1590818429,0,82271ba8,33384696094130183">哈哈哈</d><d p="99.82000,1,25,16777215,1590814312,0,2a8d1b16,33382537640804359">⎛⎝≥⏝⏝≤⎠⎞    ⎛⎝≥⏝⏝≤⎠⎞    ⎛⎝≥⏝⏝≤⎠⎞    ⎛⎝≥⏝⏝≤⎠⎞    ⎛⎝≥⏝⏝≤⎠⎞   ⎛⎝≥⏝⏝≤⎠⎞</d><d p="88.98000,1,25,16777215,1590814290,0,2a8d1b16,33382526204510211">▄▅▆▇█▇▆▅▄▄▅▆▇█▇▆▅▄▄▅▆▇█▇▆▅▄▄▅▆▇█▇▆▅▄▄▅▆▇█▇▆▅▄▄▅▆▇█▇▆▅▄▄▅▆▇█▇▆▅▄▄▅▆▇█▇▆▅▄▄▅▆</d><d p="68.20000,1,25,16777215,1590761106,0,e16b2f93,33354642566414339">sucker?????</d><d p="47.57000,1,25,16777215,1590761076,0,e16b2f93,33354626552037381">英文好评</d><d p="73.73000,1,25,16777215,1590756375,0,6f9e4c56,33352162089631749">(　o=^•ェ•)o　┏━┓</d><d p="48.89800,1,25,16777215,1590727020,0,e887a881,33336771745415175">哈哈哈</d><d p="103.22000,1,25,16777215,1590673989,0,2a8d1b16,33308967794376711">⎛⎝≥⏝⏝≤⎠⎞    ⎛⎝≥⏝⏝≤⎠⎞    ⎛⎝≥⏝⏝≤⎠⎞    ⎛⎝≥⏝⏝≤⎠⎞    ⎛⎝≥⏝⏝≤⎠⎞   ⎛⎝≥⏝⏝≤⎠⎞</d><d p="50.23800,1,25,16777215,1590642698,0,40dc0d29,33292562605277187">哈哈哈哈哈哈哈</d><d p="15.91900,1,25,16777215,1590628458,0,50380be5,33285096472051717">考古尼玛呢？</d><d p="19.04800,1,25,16777215,1590550074,0,3c1bd4a3,33244000780550149">mm</d><d p="95.53700,1,25,16777215,1590499406,0,4856477d,33217436326035463">配绿的</d><d p="64.36400,1,25,16777215,1590499375,0,4856477d,33217419980308485">厉害了</d><d p="42.44700,1,25,16777215,1590499353,0,4856477d,33217408496828423">哈哈哈哈哈哈哈哈哈哈哈哈哈好好</d><d p="51.92300,1,25,16707842,1590495895,0,14b9b6e2,33215595372609543">哈哈哈哈</d><d p="104.25900,1,25,16777215,1590419515,0,f9e028d2,33175550345347075">哈哈哈哈哈哈哈哈哈哈哈哈哈哈</d><d p="55.25900,1,25,16777215,1590419466,0,f9e028d2,33175524642652163">哈哈哈哈哈哈哈哈哈去哈哈哈</d><d p="22.25800,1,25,16777215,1590419433,0,f9e028d2,33175507319652357">哈哈哈哈哈哈哈</d><d p="0.00000,1,25,15138834,1590392893,0,e956a079,33161592844058627">记得看底下的英语！！！！</d><d p="24.73400,1,25,52480,1590362640,0,dea4e3b3,33145731504668677">???</d><d p="44.89100,1,25,16777215,1590321439,0,b61dedab,33124130043199495">哈哈哈</d><d p="26.62900,1,25,16777215,1590321414,0,b61dedab,33124116952252421">？？</d><d p="24.32000,1,25,16777215,1590321405,0,b61dedab,33124112188047363">？？</d><d p="12.12100,1,25,16646914,1590311991,0,7604609a,33119176752627717">哈</d><d p="10.70600,1,25,16777215,1590211778,0,7270fd2e,33066636504727557">◤◢◤◢◤◢前方高能◤◢◤◢◤◢High energy ahead◤◢◤◢◤◢前方高能◤◢◤◢◤◢High energy ahead◤◢◤◢◤◢前方高能◤◢◤◢◤◢High energy ahead</d><d p="105.26500,1,25,52480,1590152966,0,b7435cdd,33035801662586887">绿的</d><d p="37.67800,1,25,16777215,1590145761,0,6915b23e,33032024530354181">？？？？？？？？</d><d p="68.20700,1,25,16777215,1590140769,0,99e79f98,33029406943870979">山东还没开学时代前来考古</d><d p="3.57900,1,25,16777215,1590129857,0,d24ee3ed,33023686139183109">赌船开头</d><d p="51.60100,1,25,16777215,1590128019,0,6552bf0e,33022722424963075">裂开WC</d><d p="87.60300,1,25,52480,1590053458,0,dea4e3b3,32983631078096899">靓仔</d><d p="4.41400,1,25,16777215,1589974376,0,db7a098a,32942169053986821">夏雪夏雨夏冰雹</d><d p="90.76500,1,25,16777215,1589961571,0,415cd91e,32935455712346119">欧拉欧拉you</d><d p="37.59400,1,25,38979,1589857514,0,a1e4ad6b,32880899937271811">你要的嘛</d><d p="19.15800,1,25,38979,1589857496,0,a1e4ad6b,32880890285129733">哈哈哈哈哈哈</d><d p="8.07500,1,25,16777215,1589857485,0,a1e4ad6b,32880884471824389">祖传开头</d><d p="6.24900,1,25,16777215,1589853480,0,112a7f19,32878785016627205">祖传开头</d><d p="51.70300,1,25,16777215,1589853244,0,112a7f19,32878661279940611">哈哈哈哈哈哈哈哈哈哈哈哈</d><d p="106.65500,1,25,16777215,1589802158,0,2fc6cdf9,32851877298700295">e......</d><d p="57.13800,1,25,16777215,1589696499,0,a26dda93,32796481707573251">弹幕</d><d p="108.99200,1,25,9033215,1589685700,0,4277be73,32790820070359047">⎛⎝≥⏝⏝≤⎠⎞    ⎛⎝≥⏝⏝≤⎠⎞    ⎛⎝≥⏝⏝≤⎠⎞    ⎛⎝≥⏝⏝≤⎠⎞    ⎛⎝≥⏝⏝≤⎠⎞   ⎛⎝≥⏝⏝≤⎠⎞</d><d p="30.83100,1,25,16777215,1589616824,0,4856477d,32754708806369283">灵性</d><d p="92.52400,1,25,16777215,1589499624,0,a22af279,32693262494990343">⎛⎝≥⏝⏝≤⎠⎞    ⎛⎝≥⏝⏝≤⎠⎞    ⎛⎝≥⏝⏝≤⎠⎞    ⎛⎝≥⏝⏝≤⎠⎞   ⎛⎝≥⏝⏝≤⎠</d><d p="90.43700,1,25,9599289,1589458686,0,a6868ddf,32671799194419203">卧槽</d><d p="66.12100,1,25,16777215,1589458011,0,e6b94756,32671445492957191">哈哈哈哈哈哈哈哈</d><d p="83.28100,1,25,16777215,1589447771,0,9f57d27,32666076705718279">⎛⎝≥⏝⏝≤⎠⎞    ⎛⎝≥⏝⏝≤⎠⎞    ⎛⎝≥⏝⏝≤⎠⎞    ⎛⎝≥⏝⏝≤⎠⎞    ⎛⎝≥⏝⏝≤⎠⎞   ⎛⎝≥⏝⏝≤⎠⎞</d><d p="42.37900,1,25,38979,1589415106,0,eebe5958,32648950841344003">哈哈哈</d><d p="42.37900,1,25,38979,1589415099,0,eebe5958,32648947057033219">哈哈哈哈哈哈哈哈</d><d p="68.44600,1,25,16777215,1589375266,0,13dc5c0b,32628063293931527">？？</d><d p="58.97900,1,25,16777215,1589375256,0,13dc5c0b,32628057692962819">？？？</d><d p="21.95700,1,25,16777215,1589353836,0,9763b359,32616827709292547">抖音已盗</d><d p="60.80300,1,25,16777215,1589327953,0,112a7f19,32603257191792643">？</d><d p="45.77200,1,25,16777215,1589327936,0,112a7f19,32603248451387395">绿</d><d p="34.04000,1,25,16777215,1589326869,0,112a7f19,32602689245806597">路的</d><d p="25.58800,1,25,16777215,1589274336,0,bf5342a7,32575146883547141">▅▆▇█▇▆▅▄▄▅▆▇█▇▆▄▄▅▆▇█▇▆▅▄▄▅▆▇█▇▆▅▄▄▅▆▇█▇▆▅▄▄▅▆▇█▇▆▅▄▄▅▆▇█▇▆▅▄▄▅▆▇█▇▆▅▄▄▅▆▇█▇▆▄▄▅▆█▇▆▅▄▅▆▇█▇▅▆▇█▇▆▅▄▄</d><d p="26.15700,1,25,15138834,1589264329,0,ca13f70b,32569900287393797">舒兰时代</d><d p="82.96900,1,25,16777215,1589252421,0,def63ee7,32563656900214787">⎛⎝≥⏝⏝≤⎠⎞    ⎛⎝≥⏝⏝≤⎠⎞    ⎛⎝≥⏝⏝≤⎠⎞    ⎛⎝≥⏝⏝≤⎠⎞    ⎛⎝≥⏝⏝≤⎠⎞</d><d p="77.62000,1,25,16777215,1589218104,0,fad06465,32545664741146627">哈哈哈哈</d><d p="91.51900,1,25,16777215,1589202090,0,afa5e4c5,32537268888010759">put your D in my va 这是什么虎狼之词</d><d p="97.99800,1,25,16777215,1589114935,0,b26d3758,32491574488203267">鬼畜成功</d><d p="77.07300,1,25,16777215,1589114914,0,b26d3758,32491563495981061">刘哦</d><d p="66.47100,1,25,16777215,1589114903,0,b26d3758,32491557972606979">？？？？？</d><d p="44.43400,1,25,9487136,1589040642,0,61c37e7b,32452623949365251">哈哈哈哈哈哈</d><d p="60.60300,1,25,16777215,1589030021,0,3614ef07,32447055109554181">\</d><d p="90.19600,1,25,408,1588998934,0,77ebd70f,32430756566401031">⎛⎝≥⏝⏝≤⎠⎞    ⎛⎝≥⏝⏝≤⎠⎞    ⎛⎝≥⏝⏝≤⎠⎞    ⎛⎝≥⏝⏝≤⎠⎞   ⎛⎝≥⏝⏝≤⎠⎞</d><d p="35.10000,1,25,52480,1588955548,0,687e6367,32408009818243141">罗          德           曼</d><d p="46.85800,1,25,52480,1588917375,0,1018c1e7,32387996068610053">？？？？？？</d><d p="41.97300,1,25,16777215,1588889549,0,8cbba1a6,32373407681609733">哈哈哈哈哈</d><d p="81.07300,1,25,16777215,1588848845,0,66a5533f,32352066816442373">⎛⎝≥⏝⏝≤⎠⎞    ⎛⎝≥⏝⏝≤⎠⎞    ⎛⎝≥⏝⏝≤⎠⎞    ⎛⎝≥⏝⏝≤⎠⎞    ⎛⎝≥⏝⏝≤⎠⎞   ⎛⎝≥⏝⏝≤⎠⎞</d><d p="78.69000,1,25,16707842,1588847312,0,b394f784,32351263187795973">▄▅▆▇█▇▆▅▄▄▅▆▇█▇▆▅▄▄▅▆▇█▇▆▅▄▄▅▆▇█▇▆▅▄▄▅▆▇█▇▆▅▄▄▅▆▇█▇▆▅▄▄▅▆▇█▇▆▅▄▄▅▆▇█▇▆▅▄▄▅▆▇█▇▆▄▄▅▆▇█▇▆▅▄▄▅▆▇█▇▆▅▄▄▅</d><d p="62.81900,1,25,16707842,1588847283,0,b394f784,32351247780544515">▄▅▆▇█▇▆▅▄▄▅▆▇█▇▆▅▄▄▅▆▇█▇▆▅▄▄▅▆▇█▇▆▅▄▄▅▆▇█▇▆▅▄▄▅▆▇█▇▆▅▄▄▅▆▇█▇▆▅▄▄▅▆▇█▇▆▅▄▄▅▆▇█▇▆▄▄▅▆▇█▇▆▅▄▄▅▆▇█▇▆▅▄</d><d p="100.63700,1,25,16777215,1588825897,0,e68d5f64,32340035580723203">日文字幕？</d><d p="26.10100,1,25,16777215,1588825823,0,e68d5f64,32339996510257155">英文字幕是认真的吗</d><d p="50.96200,1,25,16777215,1588741936,0,a945f539,32296015760457735">哈哈哈哈</d><d p="59.59400,1,25,16777215,1588739396,0,880d1c13,32294684208398339">？？？？？？？？？？？？？？？？</d><d p="5.13100,1,25,52480,1588669993,0,626922b0,32258296720654343">⎛⎝≥⏝⏝≤⎠⎞    ⎛⎝≥⏝⏝≤⎠⎞    ⎛⎝≥⏝⏝≤⎠⎞    ⎛⎝≥⏝⏝≤⎠⎞    ⎛⎝≥⏝⏝≤⎠⎞   ⎛⎝≥⏝⏝≤⎠⎞⎛⎝≥⏝⏝≤⎠⎞    ⎛⎝≥⏝⏝≤⎠⎞    ⎛⎝≥⏝⏝≤⎠⎞</d><d p="103.88700,1,25,16777215,1588669977,0,626922b0,32258288527081479">⎛⎝≥⏝⏝≤⎠⎞    ⎛⎝≥⏝⏝≤⎠⎞    ⎛⎝≥⏝⏝≤⎠⎞    ⎛⎝≥⏝⏝≤⎠⎞    ⎛⎝≥⏝⏝≤⎠⎞   ⎛⎝≥⏝⏝≤⎠⎞⎛⎝≥⏝⏝≤⎠⎞    ⎛⎝≥⏝⏝≤⎠⎞    ⎛⎝≥⏝⏝≤⎠⎞</d><d p="42.79900,1,25,16777215,1588669617,0,95c2e17c,32258099524927495">都是虎狼之词哈哈哈哈</d><d p="97.71200,1,25,16777215,1588666170,0,155789e3,32256292409573381">⎛⎝≥⏝⏝≤⎠⎞    ⎛⎝≥⏝⏝≤⎠⎞    ⎛⎝≥⏝⏝≤⎠⎞    ⎛⎝≥⏝⏝≤⎠⎞   ⎛⎝≥⏝⏝≤⎠</d><d p="13.47900,1,25,16777215,1588657532,0,e887a881,32251763809058821">不知道看了多少遍</d><d p="2.01200,1,25,16777215,1588595615,0,50050187,32219301310103557">多人运动时代考古</d><d p="69.69700,1,25,16777215,1588583060,0,cdc36f0a,32212718806106117">哈哈</d><d p="38.53700,1,25,16777215,1588583021,0,cdc36f0a,32212698769915911">胖</d><d p="5.09700,1,25,16777215,1588582951,0,cdc36f0a,32212662067134467">祖传开头又开始了</d><d p="53.28300,1,25,16777215,1588579250,0,d2ee02ba,32210721726529543">哈哈哈哈哈哈哈哈哈哈哈哈哈哈哈哈哈哈哈</d><d p="37.26800,1,25,16777215,1588579235,0,d2ee02ba,32210713396641799">哈哈哈哈哈哈哈哈哈哈哈哈哈哈哈哈哈哈哈哈</d><d p="9.54800,1,25,16777215,1588515778,0,e9f67161,32177443620519943">祖传开头呢？</d><d p="109.00000,1,25,16777215,1588473942,0,f3fac8ef,32155509925609477">！</d><d p="101.45500,1,25,16777215,1588473934,0,f3fac8ef,32155505606524931">！！！！！！！！！！！！！！！！！！</d><d p="88.93400,1,25,16777215,1588473922,0,f3fac8ef,32155499072323591">！！！！！！！！！！！！！！！</d><d p="82.28300,1,25,16777215,1588473915,0,f3fac8ef,32155495559069699">！！！！！！！！！！！！！！！</d><d p="76.02900,1,25,16777215,1588473909,0,f3fac8ef,32155492275454019">！！！！！！！！！！！！！！</d><d p="69.51900,1,25,16777215,1588473902,0,f3fac8ef,32155488859717635">！！！！！！！！！！！！！！</d><d p="59.38500,1,25,16777215,1588473892,0,f3fac8ef,32155483566506055">！！！！！！！！！！！！！！</d><d p="13.54600,1,25,16777215,1588473846,0,f3fac8ef,32155459510599683">祖传开头</d><d p="27.25600,1,25,16777215,1588432317,0,281ff078,32133686366306307">wc，你是两年半的练习生吗？</d><d p="7.67200,1,25,16777215,1588432146,0,281ff078,32133596538470403">在来亿遍</d><d p="3.29300,1,25,16777215,1588414598,0,8da34e6b,32124396580634631">来了来了</d><d p="17.50400,1,25,16777215,1588414507,0,8da34e6b,32124348486647815">来了来了</d><d p="23.86000,1,25,16777215,1588395056,0,ccd2efa3,32114150863273987">火钳刘明</d><d p="41.64300,1,25,16777215,1588390940,0,cdd27e85,32111992982994949">祖传开头</d><d p="45.27900,1,25,16777215,1588364169,0,9fd76d89,32097957258985477">哈哈哈哈哈哈哈哈哈哈哈哈哈哈哈哈哈哈哈</d><d p="102.59200,1,25,10546688,1588340721,0,c222cae5,32085663398494215">hhhhhhhhhhhhhhhhhhhhhhhhhhhhhhhhhhhhh</d><d p="79.54000,1,25,10546688,1588340686,0,c222cae5,32085645124435973">由 YELLOW 转 GREEN</d><d p="27.90500,1,25,16646914,1588340566,0,c222cae5,32085582255489027">2 years half practiser?</d><d p="72.16700,1,25,16777215,1588328700,0,b62133f2,32079360826015749">这是什么虎狼之词</d><d p="56.98200,1,25,16777215,1588326973,0,25781f41,32078455596646405">⎛⎝≥⏝⏝≤⎠⎞    ⎛⎝≥⏝⏝≤⎠⎞    ⎛⎝≥⏝⏝≤⎠⎞    ⎛⎝≥⏝⏝≤⎠⎞   ⎛⎝≥⏝⏝≤⎠⎞</d><d p="101.04500,1,25,16777215,1588307167,0,8194aa65,32068071788118021">⎛⎝≥⏝⏝≤⎠⎞    ⎛⎝≥⏝⏝≤⎠⎞    ⎛⎝≥⏝⏝≤⎠⎞    ⎛⎝≥⏝⏝≤⎠⎞    ⎛⎝≥⏝⏝≤⎠⎞   ⎛⎝≥⏝⏝≤⎠⎞⎛⎝≥⏝⏝≤⎠⎞    ⎛⎝≥⏝⏝≤⎠⎞</d><d p="89.57200,1,25,16777215,1588307156,0,8194aa65,32068065777156101">⎛⎝≥⏝⏝≤⎠⎞    ⎛⎝≥⏝⏝≤⎠⎞    ⎛⎝≥⏝⏝≤⎠⎞    ⎛⎝≥⏝⏝≤⎠⎞    ⎛⎝≥⏝⏝≤⎠⎞   ⎛⎝≥⏝⏝≤⎠⎞⎛⎝≥⏝⏝≤⎠⎞    ⎛⎝≥⏝⏝≤⎠⎞    ⎛⎝≥⏝⏝≤⎠⎞</d><d p="42.09900,1,25,16777215,1588246033,0,8bd7f953,32036019802472455">？？？</d><d p="73.75000,1,25,16777215,1588217045,0,c386bcff,32020821899214853">哈哈哈哈哈哈哈哈哈哈哈哈哈哈哈哈哈哈哈哈哈</d><d p="88.74100,1,25,16777215,1588212212,0,e887a881,32018287838625799">旋律不错</d><d p="56.77800,1,25,16777215,1588071623,0,19611c63,31944578594504707">哈哈哈哈</d><d p="50.57900,1,25,16777215,1588045601,0,dd6e9c86,31930935618830343">我来证明你开d</d><d p="61.35500,1,25,16777215,1587993514,0,1815c7e5,31903627163467779">紫妹小时候演技就很棒</d><d p="50.68800,1,25,16777215,1587993491,0,1815c7e5,31903614942838787">紫妹小时候就很可爱</d><d p="8.74000,1,25,16777215,1587973537,0,1275aeb2,31893153228783619">钉钉时代已经过去了，我们迎来了永动机时代</d><d p="107.80400,1,25,16777215,1587964095,0,6db4f13e,31888202995335171">噜噜噜</d><d p="59.80600,1,25,16777215,1587964047,0,6db4f13e,31888177765548039">快点打我</d><d p="24.25800,1,25,16777215,1587953657,0,41548e4c,31882730571563011">⎛⎝≥⏝⏝≤⎠⎞    ⎛⎝≥⏝⏝≤⎠⎞    ⎛⎝≥⏝⏝≤⎠⎞    ⎛⎝≥⏝⏝≤⎠⎞    ⎛⎝≥⏝⏝≤⎠⎞⎛⎝≥⏝⏝≤⎠⎞    ⎛⎝≥⏝⏝≤⎠⎞    ⎛⎝≥⏝⏝≤⎠⎞    ⎛⎝≥⏝⏝≤⎠⎞</d><d p="27.52200,1,25,38979,1587899674,0,93d79e71,31854428001140739">给他带顶帽</d><d p="21.62000,1,25,16777215,1587890037,0,73834ec5,31849375366905861">哈哈哈</d><d p="37.50200,1,25,52480,1587821547,0,f0826cd5,31813466863960069">虎狼之词</d><d p="34.88000,1,25,16777215,1587821533,0,f0826cd5,31813459364544519">虎狼之词</d><d p="81.36500,1,25,52480,1587813880,0,e6b9c411,31809447155728387">哦？</d><d p="8.21000,1,25,52480,1587783198,0,938dd429,31793361197203463">祖传开头</d><d p="6.86400,1,25,52480,1587783179,0,938dd429,31793351169146885">祖传开头绿</d><d p="7.26100,1,25,16777215,1587717554,0,d59fa36b,31758944519061511">再来亿次</d><d p="105.17200,1,25,16777215,1587705182,0,df62a911,31752457959768067">哈哈哈哈哈哈哈哈</d><d p="83.65600,1,25,16777215,1587645033,0,fc66d12c,31720922845544455">？？？</d><d p="32.23900,1,25,16777215,1587557775,0,a48a9e80,31675174400557063">哈哈哈哈嗝</d><d p="52.32900,1,25,16777215,1587549152,0,e9d72ed4,31670653519134723">⎛⎝≥⏝⏝≤⎠⎞    ⎛⎝≥⏝⏝≤⎠⎞    ⎛⎝≥⏝⏝≤⎠⎞    ⎛⎝≥⏝⏝≤⎠⎞   ⎛⎝≥⏝⏝≤⎠⎞</d><d p="63.75200,1,25,16777215,1587547048,0,d99bc32a,31669550155038723">⎛⎝≥⏝⏝≤⎠⎞    ⎛⎝≥⏝⏝≤⎠⎞    ⎛⎝≥⏝⏝≤⎠⎞    ⎛⎝≥⏝⏝≤⎠⎞    ⎛⎝≥⏝⏝≤⎠⎞   ⎛⎝≥⏝⏝≤⎠⎞</d><d p="23.15800,1,25,16777215,1587545323,0,8f55298d,31668646145687559">。。？？？？</d><d p="18.95800,1,25,16777215,1587545316,0,8f55298d,31668642227683335">。。。。</d><d p="21.81800,1,25,16777215,1587545081,0,9508dcd1,31668519127482375">哈哈哈哈</d><d p="29.74800,1,25,52480,1587533023,0,fde9e7a7,31662197208776707">________________________________________________</d><d p="20.50200,1,25,52480,1587533014,0,fde9e7a7,31662192286236679">_____________________________________________________________</d><d p="108.99200,1,25,16777215,1587486183,0,db327d63,31637639465533445">哈哈哈哈哈哈哈哈哈</d><d p="33.33200,1,25,16777215,1587483129,0,e0af6f5f,31636038194036741">优秀</d><d p="35.58500,1,25,16777215,1587482815,0,dc41c7bb,31635873517273093">DY以盗</d><d p="11.58800,1,25,16777215,1587482790,0,dc41c7bb,31635860491862023">DY</d><d p="46.44800,1,25,16777215,1587475886,0,8dbc68ba,31632241192861703">牛</d><d p="13.89900,1,25,16777215,1587475523,0,e1528c9e,31632050685476867">▅▆▇█▇▆▅▄▄▅▆▇█▇▆▄▄▅▆▇█▇▆▅▄▄▅▆▇█▇▆▅▄▄▅▆▇█▇▆▅▄▄▅▆▇█▇▆▅▄▄▅▆▇█▇▆▅▄▄▅▆▇█▇▆▅▄▄▅▆▇█▇▆▄▄▅▆█▇▆▅▄▅▆▇█▇▅▆▇█▇▆▅▄▄</d><d p="33.99600,1,25,9599289,1587466528,0,3e10c815,31627334608486407">哈哈哈哈哈哈哈哈哈哈哈哈哈哈哈哈哈哈哈哈哈</d><d p="16.12500,1,25,16777215,1587458482,0,b03d28b4,31623116220792839">⎛⎝≥⏝⏝≤⎠⎞    ⎛⎝≥⏝⏝≤⎠⎞    ⎛⎝≥⏝⏝≤⎠⎞    ⎛⎝≥⏝⏝≤⎠⎞    ⎛⎝≥⏝⏝≤⎠⎞⎛⎝≥⏝⏝≤⎠⎞    ⎛⎝≥⏝⏝≤⎠⎞    ⎛⎝≥⏝⏝≤⎠⎞    ⎛⎝≥⏝⏝≤⎠⎞</d><d p="48.04300,1,25,16765698,1587372651,0,cb6d952f,31578115910139907">hhhhhc</d><d p="35.83700,1,25,16777215,1587359382,0,b2ac1e56,31571159280517127">哈哈哈哈哈哈。</d><d p="63.50500,1,25,16776960,1587350991,0,3d535155,31566759735590919">？？？？？？？？？？？？？？？？？？？？？？？？？？？？？？？？？？？？？？？？？？？？？？？？？？？？？？？？？？？？？？？？？？？？？？？？？？？？？？？？？？？？？？？？？？</d><d p="106.42600,1,25,38979,1587310944,0,5d2d4bee,31545763823091719">？？？？？？？？？？？？？？？？</d><d p="105.73700,1,25,16707842,1587297626,0,36f273ac,31538781306224643">看英文字母</d><d p="50.90500,1,25,38979,1587290863,0,5bcbd340,31535235521314823">哈哈哈哈哈哈哈哈哈哈哈哈哈哈哈哈哈哈哈哈哈哈哈哈哈哈哈哈哈哈哈哈哈哈哈哈哈哈哈哈哈哈哈哈哈哈哈哈哈哈哈哈哈哈哈哈哈哈哈哈哈哈哈哈哈</d><d p="42.19400,1,25,38979,1587290832,0,5bcbd340,31535219153043463">哈哈哈哈哈哈哈哈哈哈哈哈哈哈哈哈哈哈哈哈哈哈哈哈哈哈哈哈哈哈哈哈哈哈哈哈哈哈哈哈哈哈哈哈哈哈哈哈哈哈哈哈哈哈哈哈哈哈哈哈哈哈哈哈哈哈哈哈哈哈哈哈哈哈哈哈哈哈哈哈哈哈哈哈哈哈哈哈哈哈哈哈哈哈哈哈哈哈</d><d p="6.25900,1,25,16777215,1587282737,0,31bb80af,31530975283904517">撒贝宁小朋盆友</d><d p="6.71800,1,25,16777215,1587175851,0,e887a881,31474936212094981">祖传开头</d><d p="107.44400,1,25,16777215,1587122691,0,57b0c562,31447065011159047">下次也不一定</d><d p="29.26300,1,25,16777215,1587100370,0,c3d3ee7,31435362575843331">？？？？？</d><d p="21.81400,1,25,16777215,1587092880,0,686aafec,31431435722686467">哈哈哈哈哈哈</d><d p="100.57400,1,25,16777215,1587088024,0,bfb3b181,31428889357582339">变色</d><d p="71.48000,1,25,16777215,1587035582,0,2b7ee03a,31401395086163971">喵内喵内</d><d p="9.27800,1,25,16777215,1587035497,0,d81a773d,31401350456672261">▄▅▆▇█▇▆▅▄▄▅▆▇█▇▆▅▄▄▅▆▇█▇▆▅▄▄▅▆▇█▇▆▅▄▄▅▆▇█▇▆▅▄▄▅▆█▇▆▅▄▄▅▆▇█▇▆▅▄▄▅▆▇█▇▆▅▄▄▅▆▇█▇▆▅▄▄▅▆▇█▇▆▅▄▄▅▆▇█▇▆</d><d p="79.78800,1,25,16777215,1587024542,0,431235a1,31395606619488259">注意看英文</d><d p="30.11300,1,25,16777215,1587024477,0,431235a1,31395572573798403">英文是原文注意看</d><d p="42.70800,1,25,16777215,1587015929,0,3a687ed6,31391090835718151">红红火火恍恍惚惚</d><d p="83.64000,1,25,16777215,1587008672,0,a886f506,31387286417440771">哈哈哈哈哈哈哈哈哈哈哈哈哈哈哈哈哈哈哈哈</d><d p="65.75200,1,25,16777215,1587006217,0,201fdfa6,31385999365898243">哈哈哈哈呵呵呵呵嘿嘿嘿哈哈哈哈呵呵呵呵嘿嘿嘿</d><d p="52.35700,1,25,16777215,1587006204,0,201fdfa6,31385992365604871">哈哈哈哈呵呵呵呵嘿嘿嘿哈哈哈哈呵呵呵呵嘿嘿嘿哈哈哈哈呵呵呵呵嘿嘿嘿哈哈哈哈呵呵呵呵嘿嘿嘿哈哈哈哈呵呵呵呵哈哈</d><d p="100.74100,1,25,16777215,1586997633,0,a886f506,31381498482393093">哈哈哈哈哈哈</d><d p="107.20000,1,25,16777215,1586941749,0,f69292d4,31352199188054023">开头见</d><d p="100.19700,1,25,16777215,1586939197,0,a886f506,31350861134823427">哈哈哈哈好</d><d p="79.18700,1,25,16777215,1586939176,0,a886f506,31350850116911111">哈哈哈哈</d><d p="93.79800,1,25,16777215,1586938774,0,a886f506,31350639646736387">哈哈哈哈哈</d><d p="51.98200,1,25,16777215,1586938732,0,a886f506,31350617734119427">哈哈哈哈哈哈哈哈哈</d><d p="12.60400,1,25,16777215,1586938565,0,a886f506,31350530070020099">hhhhhhhhhhh</d><d p="30.25400,1,25,16777215,1586938361,0,a886f506,31350423235854343">哈哈哈哈哈哈哈哈哈哈哈哈哈哈哈哈哈哈哈</d><d p="57.77400,1,25,16777215,1586928791,0,f8d3c7d9,31345405844258821">害怕</d><d p="10.52900,1,25,16646914,1586922182,0,430ab4f6,31341940413300739">奥利给！！！！！！！！！！！！！！！！！！！！！！！！！！！！！！！！！！！！！！！！！！！！！！！</d><d p="80.55800,1,25,16776960,1586909894,0,e48df09e,31335498150051847">WTG</d><d p="50.72800,1,25,16646914,1586909864,0,e48df09e,31335482185482245">哈哈哈哈哈</d><d p="44.03800,1,25,16777215,1586909857,0,e48df09e,31335478674849799">哈哈哈哈</d><d p="92.97800,1,25,16777215,1586872035,0,cf33641f,31315648941391875">曹操的英文翻译?f**k f**k?</d><d p="59.54800,1,25,16777215,1586842488,0,aeefb911,31300157744611333">哈哈哈哈哈哈哈哈</d><d p="31.15100,1,25,16777215,1586836897,0,b53570de,31297226588815365">哈哈哈哈哈哈哈哈哈哈哈哈哈哈哈哈哈</d><d p="59.96600,1,25,16707842,1586831101,0,46d2b047,31294187746885637">？？？</d><d p="11.90300,1,25,16777215,1586782089,0,c7285240,31268491283136517">祖传开头呢</d><d p="31.27300,1,25,16777215,1586780631,0,9508dcd1,31267727282274307">哈哈哈</d><d p="108.83000,1,25,16777215,1586776831,0,e4c76f81,31265734997311495">。。</d><d p="100.43000,1,25,16777215,1586760504,0,d64075e9,31257174875308037">。                                                                                                  。</d><d p="76.96900,1,25,16777215,1586760481,0,d64075e9,31257162565550087">。</d><d p="80.34300,1,25,16777215,1586681730,0,4d2d1ecc,31215874516451333">⎛⎝≥⏝⏝≤⎠⎞   ⎛⎝≥⏝⏝≤⎠⎞⎛⎝  ≥⏝⏝≤⎠⎞    ⎛⎝≥⏝⏝≤⎠⎞    ⎛⎝≥⏝⏝≤⎠⎞⎛⎝≥⏝⏝≤⎠⎞   ⎛⎝≥⏝⏝≤⎠⎞⎛⎝  ≥⏝⏝≤⎠⎞    ⎛⎝≥⏝⏝≤⎠⎞</d><d p="65.45500,1,25,16777215,1586681715,0,4d2d1ecc,31215866695647237">⎛⎝≥⏝⏝≤⎠⎞   ⎛⎝≥⏝⏝≤⎠⎞⎛⎝  ≥⏝⏝≤⎠⎞    ⎛⎝≥⏝⏝≤⎠⎞    ⎛⎝≥⏝⏝≤⎠⎞</d><d p="70.11300,1,25,16777215,1586618551,0,b7381a38,31182750681137157">？？？？</d><d p="17.05500,1,25,16777215,1586618498,0,b7381a38,31182722844065795">淦</d><d p="28.00200,1,25,16777215,1586531290,0,8d6ea738,31137000590409731">哈哈哈哈哈哈</d><d p="32.40400,1,25,6830715,1586516949,0,9985cd4c,31129481656664071">卧操</d><d p="40.17000,1,25,52480,1586513207,0,6d5174f8,31127519947653125">⎛⎝≥⏝⏝≤⎠⎞    ⎛⎝≥⏝⏝≤⎠⎞    ⎛⎝≥⏝⏝≤⎠⎞    ⎛⎝≥⏝⏝≤⎠⎞   ⎛⎝≥⏝⏝≤⎠</d><d p="20.49200,1,25,52480,1586494779,0,6b0f227f,31117858379923461">⎛⎝≥⏝⏝≤⎠⎞    ⎛⎝≥⏝⏝≤⎠⎞      ⎛⎝≥⏝⏝≤⎠⎞   ⎛⎝≥⏝⏝≤⎠⎞⎛⎝≥⏝⏝≤⎠⎞    ⎛⎝≥⏝⏝≤⎠⎞    ⎛⎝≥⏝⏝≤⎠⎞    ⎛⎝≥⏝⏝≤⎠⎞   ⎛⎝≥⏝⏝≤⎠⎞</d><d p="67.05100,1,25,16776960,1586488901,0,ae945e2f,31114776568922181">▂▃▄▅▆▅▄▃▂▂▃▄▅▆▅▄▃▂▂▃▄▅▆▅▄▃▂▂▃▂▂▃▄▅▆▆▅▄▃▂▂▃▄▂▃▄▅▆▅▄▂▃▄▅▆▅▄▃▂▂▃▄▅▆▅▄▃▂▂▃▄▅▆▅▄▃▂▂▃▂▂▃▄▅▆▆▅▄▃▂▂▃▄▂▃</d><d p="60.65600,1,25,16777215,1586488875,0,ae945e2f,31114762901782535">⎛⎝≥⏝⏝≤⎠⎞    ⎛⎝≥⏝⏝≤⎠⎞    ⎛⎝≥⏝⏝≤⎠⎞    ⎛⎝≥⏝⏝≤⎠⎞    ⎛⎝≥⏝⏝≤⎠⎞   ⎛⎝≥⏝⏝≤⎠⎞</d><d p="23.74200,1,25,16777215,1586439504,0,223be15f,31088878144192583">爱是一道光，绿到你发慌</d><d p="80.46600,1,25,16777215,1586433707,0,253384be,31085839212085255">⎛⎝≥⏝⏝≤⎠⎞    ⎛⎝≥⏝⏝≤⎠⎞    ⎛⎝≥⏝⏝≤⎠⎞    ⎛⎝≥⏝⏝≤⎠⎞    ⎛⎝≥⏝⏝≤⎠⎞</d><d p="43.34500,1,25,16777215,1586423930,0,56399465,31080712944222215">⎛⎝≥⏝⏝≤⎠⎞    ⎛⎝≥⏝⏝≤⎠⎞    ⎛⎝≥⏝⏝≤⎠⎞    ⎛⎝≥⏝⏝≤⎠⎞   ⎛⎝≥⏝⏝≤⎠</d><d p="97.00900,1,25,16777215,1586415905,0,2550884e,31076505607471109">有病吧</d><d p="29.18700,1,25,16707842,1586410204,0,a25bed94,31073516594397191">yellow?????????</d><d p="58.76900,1,25,16777215,1586398476,0,c2b8e415,31067367765704709">⎛⎝≥⏝⏝≤⎠⎞    ⎛⎝≥⏝⏝≤⎠⎞    ⎛⎝≥⏝⏝≤⎠⎞    ⎛⎝≥⏝⏝≤⎠⎞   ⎛⎝≥⏝⏝≤⎠⎞  ⎛⎝≥⏝⏝≤⎠⎞    ⎛⎝≥⏝⏝≤⎠⎞    ⎛⎝≥⏝⏝≤⎠⎞   ⎛⎝≥⏝⏝≤⎠⎞</d><d p="10.18700,1,25,16777215,1586364981,0,b0c29d02,31049806580809731">我想把这玩意染成绿</d><d p="3.97800,1,25,16777215,1586351971,0,9749dbab,31042985958834181">恭喜你发现宝藏歌曲（手动滑稽</d><d p="17.70000,1,25,16777215,1586348979,0,b3675852,31041417261350979">钉钉时代</d><d p="98.21300,1,25,16776960,1586334608,0,5564b17,31033882809729029">？？？？？？？？？？？？？？？？？？？？？？？？？？？？？？？？？？？？？？？？？？？？？？？？？？？？？？？？？？？？？？？？？？？？？？？？？？？？？？？？？？？？？？？？？？？？？？？？？？？？</d><d p="103.10900,1,25,16777215,1586324462,0,dfbc1676,31028562957434951">哈哈哈哈哈哈哈哈哈哈哈哈哈哈哈哈哈哈哈哈哈哈哈哈哈哈哈哈哈哈哈哈哈哈哈哈哈哈哈哈哈哈哈哈哈哈哈哈哈哈哈哈哈哈哈哈哈哈哈哈哈哈哈哈哈哈哈哈哈哈哈哈哈哈哈哈哈哈哈哈哈哈哈哈哈哈哈哈哈哈哈哈哈哈哈哈哈哈哈哈</d><d p="55.53000,1,25,16777215,1586321215,0,128f51c4,31026860715409411">⎛⎝≥⏝⏝≤⎠⎞    ⎛⎝≥⏝⏝≤⎠⎞    ⎛⎝≥⏝⏝≤⎠⎞    ⎛⎝≥⏝⏝≤⎠⎞   ⎛⎝≥⏝⏝≤⎠⎞  ⎛⎝≥⏝⏝≤⎠⎞    ⎛⎝≥⏝⏝≤⎠⎞    ⎛⎝≥⏝⏝≤⎠⎞   ⎛⎝≥⏝⏝≤⎠⎞</d><d p="6.02500,1,25,16777215,1586320079,0,530b4c3f,31026265193447429">▄▅▆▇█▇▆▅▄▄▅▆▇█▇▆▅▄▄▅▆▇█▇▆▅▄▄▅▆▇█▇▆▅▄▄▅▆▇█▇▆▅▄▄▅▆▇█▇▆▅▄▄▅▆▇█▇▆▅▄▄▅▆▇█▇▆▅▄▄▅▆▇█▇▆▅▄▄▅▆▇█▇▆▅▄▄▅▆▇█▇▆▅▄</d><d p="42.38900,1,25,16777215,1586318031,0,9394e5c5,31025191321075715">刘星：我想把这玩意染成绿的</d><d p="84.52800,1,25,16777215,1586309783,0,8a5c4c8d,31020867157229571">⎛⎝≥⏝⏝≤⎠⎞    ⎛⎝≥⏝⏝≤⎠⎞    ⎛⎝≥⏝⏝≤⎠⎞    ⎛⎝≥⏝⏝≤⎠⎞    ⎛⎝≥⏝⏝≤⎠⎞   ⎛⎝≥⏝⏝≤⎠⎞</d><d p="106.53200,1,25,16777215,1586305187,0,bcb260b1,31018457398509635">(((((ી(･◡･)ʃ)))))</d><d p="25.98100,1,25,16777215,1586271955,0,10b125ee,31001034233479173">哈哈哈哈哈哈哈哈哈哈啊哈哈哈哈哈哈哈哈哈哈哈哈哈哈哈哈哈哈哈哈哈哈哈哈哈哈啊哈哈哈哈哈哈哈哈啊哈哈哈哈啊哈哈哈哈哈哈哈啊哈哈啊哈哈啊哈哈哈啊哈啊哈哈哈哈哈哈哈啊哈哈啊哈哈啊哈哈哈啊哈哈哈哈啊哈哈哈哈哈</d><d p="73.14400,1,25,16777215,1586271888,0,10b125ee,31000999057424387">哈哈哈哈哈啊哈哈哈哈啊哈哈哈哈哈哈哈啊哈哈啊哈哈啊哈哈哈啊哈哈哈哈啊哈哈哈哈哈哈哈哈哈哈啊哈哈哈哈啊哈哈哈哈哈哈哈啊哈哈啊哈哈啊哈哈哈啊哈哈哈哈啊哈哈哈哈哈哈哈哈哈哈啊哈哈哈哈啊哈哈哈哈哈哈哈啊哈哈啊</d></i>